{"1": {"data": {"$deletedFields": ["launchAlert"], "mediaConfig": "crc4KtMwSB9CyP/2sFIqSw==,root,mediaConfig", "$type": "com.linkedin.voyager.common.Configuration", "$id": "crc4KtMwSB9CyP/2sFIqSw==,root"}, "included": [{"mprConfig": "crc4KtMwSB9CyP/2sFIqSw==,root,mediaConfig,mprConfig", "$deletedFields": [], "$type": "com.linkedin.voyager.common.MediaConfig", "$id": "crc4KtMwSB9CyP/2sFIqSw==,root,mediaConfig"}, {"$deletedFields": [], "sizes": ["crc4KtMwSB9CyP/2sFIqSw==,root,mediaConfig,mprConfig,sizes,c80b70b5-4600-4547-895f-9a29c596ab46-0", "crc4KtMwSB9CyP/2sFIqSw==,root,mediaConfig,mprConfig,sizes,c80b70b5-4600-4547-895f-9a29c596ab46-1", "crc4KtMwSB9CyP/2sFIqSw==,root,mediaConfig,mprConfig,sizes,c80b70b5-4600-4547-895f-9a29c596ab46-2", "crc4KtMwSB9CyP/2sFIqSw==,root,mediaConfig,mprConfig,sizes,c80b70b5-4600-4547-895f-9a29c596ab46-3", "crc4KtMwSB9CyP/2sFIqSw==,root,mediaConfig,mprConfig,sizes,c80b70b5-4600-4547-895f-9a29c596ab46-4", "crc4KtMwSB9CyP/2sFIqSw==,root,mediaConfig,mprConfig,sizes,c80b70b5-4600-4547-895f-9a29c596ab46-5", "crc4KtMwSB9CyP/2sFIqSw==,root,mediaConfig,mprConfig,sizes,c80b70b5-4600-4547-895f-9a29c596ab46-6", "crc4KtMwSB9CyP/2sFIqSw==,root,mediaConfig,mprConfig,sizes,c80b70b5-4600-4547-895f-9a29c596ab46-7", "crc4KtMwSB9CyP/2sFIqSw==,root,mediaConfig,mprConfig,sizes,c80b70b5-4600-4547-895f-9a29c596ab46-8", "crc4KtMwSB9CyP/2sFIqSw==,root,mediaConfig,mprConfig,sizes,c80b70b5-4600-4547-895f-9a29c596ab46-9", "crc4KtMwSB9CyP/2sFIqSw==,root,mediaConfig,mprConfig,sizes,c80b70b5-4600-4547-895f-9a29c596ab46-10", "crc4KtMwSB9CyP/2sFIqSw==,root,mediaConfig,mprConfig,sizes,c80b70b5-4600-4547-895f-9a29c596ab46-11", "crc4KtMwSB9CyP/2sFIqSw==,root,mediaConfig,mprConfig,sizes,c80b70b5-4600-4547-895f-9a29c596ab46-12", "crc4KtMwSB9CyP/2sFIqSw==,root,mediaConfig,mprConfig,sizes,c80b70b5-4600-4547-895f-9a29c596ab46-13", "crc4KtMwSB9CyP/2sFIqSw==,root,mediaConfig,mprConfig,sizes,c80b70b5-4600-4547-895f-9a29c596ab46-14", "crc4KtMwSB9CyP/2sFIqSw==,root,mediaConfig,mprConfig,sizes,c80b70b5-4600-4547-895f-9a29c596ab46-15", "crc4KtMwSB9CyP/2sFIqSw==,root,mediaConfig,mprConfig,sizes,c80b70b5-4600-4547-895f-9a29c596ab46-16", "crc4KtMwSB9CyP/2sFIqSw==,root,mediaConfig,mprConfig,sizes,c80b70b5-4600-4547-895f-9a29c596ab46-17", "crc4KtMwSB9CyP/2sFIqSw==,root,mediaConfig,mprConfig,sizes,c80b70b5-4600-4547-895f-9a29c596ab46-18", "crc4KtMwSB9CyP/2sFIqSw==,root,mediaConfig,mprConfig,sizes,c80b70b5-4600-4547-895f-9a29c596ab46-19", "crc4KtMwSB9CyP/2sFIqSw==,root,mediaConfig,mprConfig,sizes,c80b70b5-4600-4547-895f-9a29c596ab46-20", "crc4KtMwSB9CyP/2sFIqSw==,root,mediaConfig,mprConfig,sizes,c80b70b5-4600-4547-895f-9a29c596ab46-21", "crc4KtMwSB9CyP/2sFIqSw==,root,mediaConfig,mprConfig,sizes,c80b70b5-4600-4547-895f-9a29c596ab46-22", "crc4KtMwSB9CyP/2sFIqSw==,root,mediaConfig,mprConfig,sizes,c80b70b5-4600-4547-895f-9a29c596ab46-23", "crc4KtMwSB9CyP/2sFIqSw==,root,mediaConfig,mprConfig,sizes,c80b70b5-4600-4547-895f-9a29c596ab46-24"], "filters": "crc4KtMwSB9CyP/2sFIqSw==,root,mediaConfig,mprConfig,filters", "$type": "com.linkedin.voyager.common.MediaProcessorConfig", "$id": "crc4KtMwSB9CyP/2sFIqSw==,root,mediaConfig,mprConfig"}, {"cover": "https://media.licdn.com/mpr/mpr/shrinknp_{width}_{height}{+id}", "$deletedFields": [], "contain": "https://media.licdn.com/mpr/mpr/shrinknp_{width}_{height}{+id}", "original": "https://media.licdn.com/media{+id}", "fill": "https://media.licdn.com/mpr/mpr/shrink_{width}_{height}{+id}", "$type": "com.linkedin.voyager.common.MediaProcessorFilters", "$id": "crc4KtMwSB9CyP/2sFIqSw==,root,mediaConfig,mprConfig,filters"}, {"$deletedFields": [], "width": 337, "height": 120, "$type": "com.linkedin.voyager.common.MediaProcessorSize", "$id": "crc4KtMwSB9CyP/2sFIqSw==,root,mediaConfig,mprConfig,sizes,c80b70b5-4600-4547-895f-9a29c596ab46-20"}, {"$deletedFields": [], "width": 400, "height": 400, "$type": "com.linkedin.voyager.common.MediaProcessorSize", "$id": "crc4KtMwSB9CyP/2sFIqSw==,root,mediaConfig,mprConfig,sizes,c80b70b5-4600-4547-895f-9a29c596ab46-21"}, {"$deletedFields": [], "width": 506, "height": 180, "$type": "com.linkedin.voyager.common.MediaProcessorSize", "$id": "crc4KtMwSB9CyP/2sFIqSw==,root,mediaConfig,mprConfig,sizes,c80b70b5-4600-4547-895f-9a29c596ab46-22"}, {"$deletedFields": [], "width": 674, "height": 240, "$type": "com.linkedin.voyager.common.MediaProcessorSize", "$id": "crc4KtMwSB9CyP/2sFIqSw==,root,mediaConfig,mprConfig,sizes,c80b70b5-4600-4547-895f-9a29c596ab46-23"}, {"$deletedFields": [], "width": 750, "height": 750, "$type": "com.linkedin.voyager.common.MediaProcessorSize", "$id": "crc4KtMwSB9CyP/2sFIqSw==,root,mediaConfig,mprConfig,sizes,c80b70b5-4600-4547-895f-9a29c596ab46-24"}, {"$deletedFields": [], "width": 200, "height": 120, "$type": "com.linkedin.voyager.common.MediaProcessorSize", "$id": "crc4KtMwSB9CyP/2sFIqSw==,root,mediaConfig,mprConfig,sizes,c80b70b5-4600-4547-895f-9a29c596ab46-16"}, {"$deletedFields": [], "width": 200, "height": 200, "$type": "com.linkedin.voyager.common.MediaProcessorSize", "$id": "crc4KtMwSB9CyP/2sFIqSw==,root,mediaConfig,mprConfig,sizes,c80b70b5-4600-4547-895f-9a29c596ab46-17"}, {"$deletedFields": [], "width": 254, "height": 60, "$type": "com.linkedin.voyager.common.MediaProcessorSize", "$id": "crc4KtMwSB9CyP/2sFIqSw==,root,mediaConfig,mprConfig,sizes,c80b70b5-4600-4547-895f-9a29c596ab46-18"}, {"$deletedFields": [], "width": 254, "height": 92, "$type": "com.linkedin.voyager.common.MediaProcessorSize", "$id": "crc4KtMwSB9CyP/2sFIqSw==,root,mediaConfig,mprConfig,sizes,c80b70b5-4600-4547-895f-9a29c596ab46-19"}, {"$deletedFields": [], "width": 120, "height": 60, "$type": "com.linkedin.voyager.common.MediaProcessorSize", "$id": "crc4KtMwSB9CyP/2sFIqSw==,root,mediaConfig,mprConfig,sizes,c80b70b5-4600-4547-895f-9a29c596ab46-7"}, {"$deletedFields": [], "width": 120, "height": 72, "$type": "com.linkedin.voyager.common.MediaProcessorSize", "$id": "crc4KtMwSB9CyP/2sFIqSw==,root,mediaConfig,mprConfig,sizes,c80b70b5-4600-4547-895f-9a29c596ab46-8"}, {"$deletedFields": [], "width": 127, "height": 30, "$type": "com.linkedin.voyager.common.MediaProcessorSize", "$id": "crc4KtMwSB9CyP/2sFIqSw==,root,mediaConfig,mprConfig,sizes,c80b70b5-4600-4547-895f-9a29c596ab46-9"}, {"$deletedFields": [], "width": 90, "height": 54, "$type": "com.linkedin.voyager.common.MediaProcessorSize", "$id": "crc4KtMwSB9CyP/2sFIqSw==,root,mediaConfig,mprConfig,sizes,c80b70b5-4600-4547-895f-9a29c596ab46-3"}, {"$deletedFields": [], "width": 100, "height": 50, "$type": "com.linkedin.voyager.common.MediaProcessorSize", "$id": "crc4KtMwSB9CyP/2sFIqSw==,root,mediaConfig,mprConfig,sizes,c80b70b5-4600-4547-895f-9a29c596ab46-4"}, {"$deletedFields": [], "width": 100, "height": 60, "$type": "com.linkedin.voyager.common.MediaProcessorSize", "$id": "crc4KtMwSB9CyP/2sFIqSw==,root,mediaConfig,mprConfig,sizes,c80b70b5-4600-4547-895f-9a29c596ab46-5"}, {"$deletedFields": [], "width": 100, "height": 100, "$type": "com.linkedin.voyager.common.MediaProcessorSize", "$id": "crc4KtMwSB9CyP/2sFIqSw==,root,mediaConfig,mprConfig,sizes,c80b70b5-4600-4547-895f-9a29c596ab46-6"}, {"$deletedFields": [], "width": 60, "height": 30, "$type": "com.linkedin.voyager.common.MediaProcessorSize", "$id": "crc4KtMwSB9CyP/2sFIqSw==,root,mediaConfig,mprConfig,sizes,c80b70b5-4600-4547-895f-9a29c596ab46-0"}, {"$deletedFields": [], "width": 60, "height": 36, "$type": "com.linkedin.voyager.common.MediaProcessorSize", "$id": "crc4KtMwSB9CyP/2sFIqSw==,root,mediaConfig,mprConfig,sizes,c80b70b5-4600-4547-895f-9a29c596ab46-1"}, {"$deletedFields": [], "width": 127, "height": 46, "$type": "com.linkedin.voyager.common.MediaProcessorSize", "$id": "crc4KtMwSB9CyP/2sFIqSw==,root,mediaConfig,mprConfig,sizes,c80b70b5-4600-4547-895f-9a29c596ab46-10"}, {"$deletedFields": [], "width": 90, "height": 45, "$type": "com.linkedin.voyager.common.MediaProcessorSize", "$id": "crc4KtMwSB9CyP/2sFIqSw==,root,mediaConfig,mprConfig,sizes,c80b70b5-4600-4547-895f-9a29c596ab46-2"}, {"$deletedFields": [], "width": 150, "height": 75, "$type": "com.linkedin.voyager.common.MediaProcessorSize", "$id": "crc4KtMwSB9CyP/2sFIqSw==,root,mediaConfig,mprConfig,sizes,c80b70b5-4600-4547-895f-9a29c596ab46-11"}, {"$deletedFields": [], "width": 150, "height": 90, "$type": "com.linkedin.voyager.common.MediaProcessorSize", "$id": "crc4KtMwSB9CyP/2sFIqSw==,root,mediaConfig,mprConfig,sizes,c80b70b5-4600-4547-895f-9a29c596ab46-12"}, {"$deletedFields": [], "width": 191, "height": 45, "$type": "com.linkedin.voyager.common.MediaProcessorSize", "$id": "crc4KtMwSB9CyP/2sFIqSw==,root,mediaConfig,mprConfig,sizes,c80b70b5-4600-4547-895f-9a29c596ab46-13"}, {"$deletedFields": [], "width": 191, "height": 69, "$type": "com.linkedin.voyager.common.MediaProcessorSize", "$id": "crc4KtMwSB9CyP/2sFIqSw==,root,mediaConfig,mprConfig,sizes,c80b70b5-4600-4547-895f-9a29c596ab46-14"}, {"$deletedFields": [], "width": 200, "height": 100, "$type": "com.linkedin.voyager.common.MediaProcessorSize", "$id": "crc4KtMwSB9CyP/2sFIqSw==,root,mediaConfig,mprConfig,sizes,c80b70b5-4600-4547-895f-9a29c596ab46-15"}]}, "2": {"request": "/voyager/api/configuration", "status": 200, "body": "bpr-guid-339894"}, "3": {"data": {"paidProducts": ["LEARNING"], "companies": [], "$deletedFields": ["postJobsEnabled"], "memberGroup": "PREMIUM", "showStaticLearning": false, "$type": "com.linkedin.voyager.common.Nav", "$id": "M8x5UY0Zt6eGdBCiy+iKhA==,root"}, "included": []}, "4": {"request": "/voyager/api/nav", "status": 200, "body": "bpr-guid-339895"}, "5": {"data": {"canBrowseProfiles": false, "$deletedFields": [], "reactivationFeaturesEligible": true, "canViewJobAnalytics": true, "canViewWVMP": true, "canViewCompanyInsights": false, "$type": "com.linkedin.voyager.premium.FeatureAccess", "$id": "rp3HQ6ObDeupY3gQ84tYJw==,root"}, "included": []}, "6": {"request": "/voyager/api/premium/featureAccess?name=reactivationFeaturesEligible", "status": 200, "body": "bpr-guid-339896"}, "7": {"data": {"shareVisibilityType": "PUBLIC", "$deletedFields": [], "sharePublicVisibilityTooltipMessage": "urn:li:fs_mySettings:476788719,sharePublicVisibilityTooltipMessage", "entityUrn": "urn:li:fs_mySettings:476788719", "dailyRundownPushNotificationAllowed": false, "videoAutoPlay": "ALWAYS", "flagshipCrossLinkToJobSearchApp": true, "discloseAsProfileViewer": "HIDE", "mobileCalendarsAutoSyncAllowed": true, "mobileContactsAutoSyncAllowed": true, "$type": "com.linkedin.voyager.common.MySettings"}, "included": [{"$deletedFields": [], "start": 72, "length": 10, "type": {"com.linkedin.pemberly.text.Hyperlink": "urn:li:fs_mySettings:476788719,sharePublicVisibilityTooltipMessage,attributes,defc822a-69a5-4e5a-8b80-0121f94e0e11-1,type,com.linkedin.pemberly.text.Hyperlink"}, "$type": "com.linkedin.pemberly.text.Attribute", "$id": "urn:li:fs_mySettings:476788719,sharePublicVisibilityTooltipMessage,attributes,defc822a-69a5-4e5a-8b80-0121f94e0e11-1"}, {"$deletedFields": [], "start": 21, "length": 6, "type": {"com.linkedin.pemberly.text.Bold": "urn:li:fs_mySettings:476788719,sharePublicVisibilityTooltipMessage,attributes,defc822a-69a5-4e5a-8b80-0121f94e0e11-0,type,com.linkedin.pemberly.text.Bold"}, "$type": "com.linkedin.pemberly.text.Attribute", "$id": "urn:li:fs_mySettings:476788719,sharePublicVisibilityTooltipMessage,attributes,defc822a-69a5-4e5a-8b80-0121f94e0e11-0"}, {"$deletedFields": [], "attributes": ["urn:li:fs_mySettings:476788719,sharePublicVisibilityTooltipMessage,attributes,defc822a-69a5-4e5a-8b80-0121f94e0e11-0", "urn:li:fs_mySettings:476788719,sharePublicVisibilityTooltipMessage,attributes,defc822a-69a5-4e5a-8b80-0121f94e0e11-1"], "text": "Now when you post to Public, it's visible to anyone on or off LinkedIn. Learn more.", "$type": "com.linkedin.pemberly.text.AttributedText", "$id": "urn:li:fs_mySettings:476788719,sharePublicVisibilityTooltipMessage"}, {"$deletedFields": [], "$type": "com.linkedin.pemberly.text.Bold", "$id": "urn:li:fs_mySettings:476788719,sharePublicVisibilityTooltipMessage,attributes,defc822a-69a5-4e5a-8b80-0121f94e0e11-0,type,com.linkedin.pemberly.text.Bold"}, {"$deletedFields": [], "url": "https://www.linkedin.com/help/linkedin/answer/82288?lang=en", "$type": "com.linkedin.pemberly.text.Hyperlink", "$id": "urn:li:fs_mySettings:476788719,sharePublicVisibilityTooltipMessage,attributes,defc822a-69a5-4e5a-8b80-0121f94e0e11-1,type,com.linkedin.pemberly.text.Hyperlink"}]}, "8": {"request": "/voyager/api/me/settings", "status": 200, "body": "bpr-guid-339897"}, "9": {"data": {"$deletedFields": [], "publicContactInfo": "qTJ8dtboEoV+oq/pm1xyeA==,root,publicContactInfo", "plainId": 476788719, "miniProfile": "urn:li:fs_miniProfile:ACoAABxrN-8Bf2FB9s1yzswU9yjVHdbJzRVGgvU", "premiumSubscriber": true, "$type": "com.linkedin.voyager.common.Me", "$id": "qTJ8dtboEoV+oq/pm1xyeA==,root"}, "included": [{"$deletedFields": [], "width": 800, "fileIdentifyingUrlPathSegment": "800_800/0?e=1529391600&v=beta&t=tG2LoSlej2zVdkcw8J8w-58PJ0LRrv3XTSIBBHsvh9s", "height": 800, "$type": "com.linkedin.common.VectorArtifact", "$id": "urn:li:fs_miniProfile:ACoAABxrN-8Bf2FB9s1yzswU9yjVHdbJzRVGgvU,picture,com.linkedin.common.VectorImage,artifacts,a62adad5-e17a-42a4-9c2d-65b443b7396e-3"}, {"$deletedFields": [], "width": 100, "fileIdentifyingUrlPathSegment": "100_100/0?e=1529391600&v=beta&t=NPHcvvxW88F84Qz4qNgxepGxntu_c95qhHmvQWgU5nw", "height": 100, "$type": "com.linkedin.common.VectorArtifact", "$id": "urn:li:fs_miniProfile:ACoAABxrN-8Bf2FB9s1yzswU9yjVHdbJzRVGgvU,picture,com.linkedin.common.VectorImage,artifacts,a62adad5-e17a-42a4-9c2d-65b443b7396e-0"}, {"$deletedFields": [], "width": 400, "fileIdentifyingUrlPathSegment": "400_400/0?e=1529391600&v=beta&t=wNM_XQh-KyyPMHzNfqwsEoh_Zbtf30YW1dkoaQXw_Xk", "height": 400, "$type": "com.linkedin.common.VectorArtifact", "$id": "urn:li:fs_miniProfile:ACoAABxrN-8Bf2FB9s1yzswU9yjVHdbJzRVGgvU,picture,com.linkedin.common.VectorImage,artifacts,a62adad5-e17a-42a4-9c2d-65b443b7396e-2"}, {"$deletedFields": [], "width": 200, "fileIdentifyingUrlPathSegment": "200_200/0?e=1529391600&v=beta&t=7XWx5gIqpSfvXbmxC9ntdG0kNlJjSJNmumX6todXo5g", "height": 200, "$type": "com.linkedin.common.VectorArtifact", "$id": "urn:li:fs_miniProfile:ACoAABxrN-8Bf2FB9s1yzswU9yjVHdbJzRVGgvU,picture,com.linkedin.common.VectorImage,artifacts,a62adad5-e17a-42a4-9c2d-65b443b7396e-1"}, {"$deletedFields": ["attribution"], "artifacts": ["urn:li:fs_miniProfile:ACoAABxrN-8Bf2FB9s1yzswU9yjVHdbJzRVGgvU,picture,com.linkedin.common.VectorImage,artifacts,a62adad5-e17a-42a4-9c2d-65b443b7396e-0", "urn:li:fs_miniProfile:ACoAABxrN-8Bf2FB9s1yzswU9yjVHdbJzRVGgvU,picture,com.linkedin.common.VectorImage,artifacts,a62adad5-e17a-42a4-9c2d-65b443b7396e-1", "urn:li:fs_miniProfile:ACoAABxrN-8Bf2FB9s1yzswU9yjVHdbJzRVGgvU,picture,com.linkedin.common.VectorImage,artifacts,a62adad5-e17a-42a4-9c2d-65b443b7396e-2", "urn:li:fs_miniProfile:ACoAABxrN-8Bf2FB9s1yzswU9yjVHdbJzRVGgvU,picture,com.linkedin.common.VectorImage,artifacts,a62adad5-e17a-42a4-9c2d-65b443b7396e-3"], "rootUrl": "https://media.licdn.com/dms/image/C5103AQGEXWTXFMHyuw/profile-displayphoto-shrink_", "$type": "com.linkedin.common.VectorImage", "$id": "urn:li:fs_miniProfile:ACoAABxrN-8Bf2FB9s1yzswU9yjVHdbJzRVGgvU,picture,com.linkedin.common.VectorImage"}, {"firstName": "Yuan", "lastName": "Li", "$deletedFields": ["backgroundImage"], "occupation": "Graduate student at University of Michigan (MSI)", "objectUrn": "urn:li:member:476788719", "entityUrn": "urn:li:fs_miniProfile:ACoAABxrN-8Bf2FB9s1yzswU9yjVHdbJzRVGgvU", "publicIdentifier": "yuanlii", "picture": {"com.linkedin.common.VectorImage": "urn:li:fs_miniProfile:ACoAABxrN-8Bf2FB9s1yzswU9yjVHdbJzRVGgvU,picture,com.linkedin.common.VectorImage"}, "trackingId": "H6gzE6HfSke/4Smsgv1/Zg==", "$type": "com.linkedin.voyager.identity.shared.MiniProfile"}, {"$deletedFields": [], "twitterHandles": [], "$type": "com.linkedin.voyager.identity.shared.PublicContactInfo", "$id": "qTJ8dtboEoV+oq/pm1xyeA==,root,publicContactInfo"}]}, "10": {"request": "/voyager/api/me", "status": 200, "body": "bpr-guid-339898"}, "11": {"data": {"$deletedFields": [], "premium": false, "influencer": false, "entityUrn": "urn:li:fs_memberBadges:ACoAAACh6xgB8s7a1lMm4grFoZBVsaZTKMHCZDs", "openLink": false, "jobSeeker": false, "$type": "com.linkedin.voyager.identity.profile.MemberBadges"}, "included": []}, "12": {"request": "/voyager/api/identity/profiles/ahmedbarshad/memberBadges", "status": 200, "body": "bpr-guid-339899"}, "13": {"data": {"$deletedFields": [], "followingInfo": "urn:li:fs_followingInfo:urn:li:member:ACoAAACh6xgB8s7a1lMm4grFoZBVsaZTKMHCZDs", "distance": "urn:li:fs_profileNetworkInfo:ACoAAACh6xgB8s7a1lMm4grFoZBVsaZTKMHCZDs,distance", "entityUrn": "urn:li:fs_profileNetworkInfo:ACoAAACh6xgB8s7a1lMm4grFoZBVsaZTKMHCZDs", "following": true, "followable": true, "followersCount": 1525, "connectionsCount": 500, "$type": "com.linkedin.voyager.identity.profile.ProfileNetworkInfo"}, "included": [{"$deletedFields": ["followingCount"], "entityUrn": "urn:li:fs_followingInfo:urn:li:member:ACoAAACh6xgB8s7a1lMm4grFoZBVsaZTKMHCZDs", "following": true, "followerCount": 1525, "$type": "com.linkedin.voyager.common.FollowingInfo"}, {"$deletedFields": [], "value": "DISTANCE_1", "$type": "com.linkedin.voyager.common.MemberDistance", "$id": "urn:li:fs_profileNetworkInfo:ACoAAACh6xgB8s7a1lMm4grFoZBVsaZTKMHCZDs,distance"}]}, "14": {"request": "/voyager/api/identity/profiles/ahmedbarshad/networkinfo", "status": 200, "body": "bpr-guid-339901"}, "15": {"data": {"elements": [], "paging": {"count": 10, "start": 0, "links": []}}, "included": []}, "16": {"request": "/voyager/api/identity/profiles/ahmedbarshad/treasuryMediaItems?q=backgroundMedia&section=EDUCATION", "status": 200, "body": "bpr-guid-339902"}, "17": {"data": {"elements": [], "paging": {"total": 0, "count": 10, "start": 0, "links": []}}, "included": []}, "18": {"request": "/voyager/api/takeovers", "status": 200, "body": "bpr-guid-339903"}, "19": {"data": {"elements": [], "paging": {"total": 0, "count": 10, "start": 0, "links": []}}, "included": []}, "20": {"request": "/voyager/api/identity/profiles/ahmedbarshad/treasuryMedia?q=sectionMedia&sectionId=summary", "status": 200, "body": "bpr-guid-339908"}, "21": {"data": {"elements": ["PuRtgfO+m94uX7YWlhWmuw==,0", "PuRtgfO+m94uX7YWlhWmuw==,1"], "paging": {"count": 10, "start": 0, "links": []}}, "included": [{"total": 1, "$deletedFields": [], "count": 8, "start": 0, "links": [], "$type": "com.linkedin.restli.common.CollectionMetadata", "$id": "PuRtgfO+m94uX7YWlhWmuw==,0,pagingInfo"}, {"total": 1, "$deletedFields": [], "count": 8, "start": 0, "links": [], "$type": "com.linkedin.restli.common.CollectionMetadata", "$id": "PuRtgfO+m94uX7YWlhWmuw==,1,pagingInfo"}, {"$deletedFields": ["attribution"], "originalHeight": 678, "url": "https://media.licdn.com/media-proxy/ext?w=800&h=800&f=n&hash=SHTHocKHfD2zB3ixEk%2BkCS0n%2BYU%3D&ora=1%2CaFBCTXdkRmpGL2lvQUFBPQ%2CxAVta9Er0Vinkhwfjw8177yE41y87UNCVordEGXyD3u0qYrdf3-4LcLYeePwuQxEcXoclAM2fvL5QTS0D8K7K9vufogn2ZbsLI24ZxUBbFImi24", "originalWidth": 1383, "$type": "com.linkedin.voyager.common.MediaProxyImage", "$id": "urn:li:fs_treasuryMedia:(ACoAAACh6xgB8s7a1lMm4grFoZBVsaZTKMHCZDs,1470908709443),data,com.linkedin.voyager.common.MediaProxyImage"}, {"$deletedFields": ["attribution"], "originalHeight": 1260, "url": "https://media.licdn.com/media-proxy/ext?w=2400&h=1260&f=n&hash=w4JvA2RErLptxAp1CanVz%2Blqfc0%3D&ora=1%2CaFBCTXdkRmpGL2lvQUFBPQ%2CxAVta5g-0R6nlh8Tw1Ek-L7Q40O550NJC4HTDy_8DnHzq8jAIiihMNiKMfau41AUfCwBhlw_fu2uQCa3H82qc9usJdEy0OPwJuKXNjJTRxIasmto1oQVEEAOuI3yI9PqQWsd9qpXfy7gYvy7RFMZKAYDxeiCH4rIDnFD1UC9eP7DKf0ADJR60bdOwgtS6p33Qp8ywItamEpl3gm96ZzvACkLssSFLHqHEVABLVWNGvZUrvq-yDamwlrNmUr6pImCBKesNa8xyUT4ze_5U1aGjXBnj3ovlTIKnNhxK0TNp_wUu1mkMZ8MclOQstTqenmprI8fwnY_rvqqDBaSfmY8gDBlYpzs6Q", "originalWidth": 2400, "$type": "com.linkedin.voyager.common.MediaProxyImage", "$id": "urn:li:fs_treasuryMedia:(ACoAAACh6xgB8s7a1lMm4grFoZBVsaZTKMHCZDs,1510752593718),data,com.linkedin.voyager.identity.profile.treasury.Link,previewImages,28d2de88-ff20-4d74-bcaa-6358df167026-0"}, {"previewImages": ["urn:li:fs_treasuryMedia:(ACoAAACh6xgB8s7a1lMm4grFoZBVsaZTKMHCZDs,1510752593718),data,com.linkedin.voyager.identity.profile.treasury.Link,previewImages,28d2de88-ff20-4d74-bcaa-6358df167026-0"], "$deletedFields": ["width", "html", "height"], "url": "https://www.meetup.com/Dallas-Sketch-App-Meetup/", "$type": "com.linkedin.voyager.identity.profile.treasury.Link", "$id": "urn:li:fs_treasuryMedia:(ACoAAACh6xgB8s7a1lMm4grFoZBVsaZTKMHCZDs,1510752593718),data,com.linkedin.voyager.identity.profile.treasury.Link"}, {"$deletedFields": [], "data": {"com.linkedin.voyager.common.MediaProxyImage": "urn:li:fs_treasuryMedia:(ACoAAACh6xgB8s7a1lMm4grFoZBVsaZTKMHCZDs,1470908709443),data,com.linkedin.voyager.common.MediaProxyImage"}, "entityUrn": "urn:li:fs_treasuryMedia:(ACoAAACh6xgB8s7a1lMm4grFoZBVsaZTKMHCZDs,1470908709443)", "customDescription": "I was part of the Design Studio that took Cisco Spark service from idea to market.", "description": "", "customTitle": "Apple's WWDC 2016 Keynote", "title": "", "$type": "com.linkedin.voyager.identity.profile.treasury.TreasuryMedia"}, {"$deletedFields": ["description", "title"], "data": {"com.linkedin.voyager.identity.profile.treasury.Link": "urn:li:fs_treasuryMedia:(ACoAAACh6xgB8s7a1lMm4grFoZBVsaZTKMHCZDs,1510752593718),data,com.linkedin.voyager.identity.profile.treasury.Link"}, "entityUrn": "urn:li:fs_treasuryMedia:(ACoAAACh6xgB8s7a1lMm4grFoZBVsaZTKMHCZDs,1510752593718)", "customDescription": "An open group for designers in the Dallas area that use Sketch App for UX design and prototyping.", "customTitle": "Dallas Sketch App Meetup (Dallas, TX)", "$type": "com.linkedin.voyager.identity.profile.treasury.TreasuryMedia"}, {"pagingInfo": "PuRtgfO+m94uX7YWlhWmuw==,0,pagingInfo", "$deletedFields": [], "mediaList": ["urn:li:fs_treasuryMedia:(ACoAAACh6xgB8s7a1lMm4grFoZBVsaZTKMHCZDs,1510752593718)"], "sectionType": "POSITION", "sectionUrn": "urn:li:position:1139733168", "$type": "com.linkedin.voyager.identity.profile.treasury.TreasuryMediaItems", "$id": "PuRtgfO+m94uX7YWlhWmuw==,0"}, {"pagingInfo": "PuRtgfO+m94uX7YWlhWmuw==,1,pagingInfo", "$deletedFields": [], "mediaList": ["urn:li:fs_treasuryMedia:(ACoAAACh6xgB8s7a1lMm4grFoZBVsaZTKMHCZDs,1470908709443)"], "sectionType": "POSITION", "sectionUrn": "urn:li:position:643251424", "$type": "com.linkedin.voyager.identity.profile.treasury.TreasuryMediaItems", "$id": "PuRtgfO+m94uX7YWlhWmuw==,1"}]}, "22": {"request": "/voyager/api/identity/profiles/ahmedbarshad/treasuryMediaItems?q=backgroundMedia&section=POSITION", "status": 200, "body": "bpr-guid-339914"}, "23": {"data": {"messagingTypingIndicators": "ALL_DISABLED", "allowOpenProfile": true, "profilePictureVisibilitySetting": "PUBLIC", "$deletedFields": [], "entityUrn": "urn:li:fs_privacySettings:ACoAABxrN-8Bf2FB9s1yzswU9yjVHdbJzRVGgvU", "showPublicProfile": true, "showPremiumSubscriberBadge": true, "publicProfilePictureVisibilitySetting": "PUBLIC", "formerNameVisibilitySetting": "CONNECTIONS", "messagingSeenReceipts": "ALL_DISABLED", "allowProfileEditBroadcasts": false, "$type": "com.linkedin.voyager.identity.profile.PrivacySettings"}, "included": []}, "24": {"request": "/voyager/api/identity/profiles/ahmedbarshad/privacySettings", "status": 200, "body": "bpr-guid-339916"}, "25": {"data": {"$deletedFields": [], "versionTag": "1038066042", "$type": "com.linkedin.voyager.identity.profile.VersionTag", "$id": "0r6QfaWPmh9Ym9pFlhcGqg==,root"}, "included": []}, "26": {"request": "/voyager/api/identity/profiles/ACoAABxrN-8Bf2FB9s1yzswU9yjVHdbJzRVGgvU/versionTag", "status": 200, "body": "bpr-guid-339917"}, "27": {"data": {"patentView": "urn:li:fs_patentView:ACoAAACh6xgB8s7a1lMm4grFoZBVsaZTKMHCZDs", "educationView": "urn:li:fs_educationView:ACoAAACh6xgB8s7a1lMm4grFoZBVsaZTKMHCZDs", "organizationView": "urn:li:fs_organizationView:ACoAAACh6xgB8s7a1lMm4grFoZBVsaZTKMHCZDs", "projectView": "urn:li:fs_projectView:ACoAAACh6xgB8s7a1lMm4grFoZBVsaZTKMHCZDs", "positionView": "urn:li:fs_positionView:ACoAAACh6xgB8s7a1lMm4grFoZBVsaZTKMHCZDs", "profile": "urn:li:fs_profile:ACoAAACh6xgB8s7a1lMm4grFoZBVsaZTKMHCZDs", "languageView": "urn:li:fs_languageView:ACoAAACh6xgB8s7a1lMm4grFoZBVsaZTKMHCZDs", "certificationView": "urn:li:fs_certificationView:ACoAAACh6xgB8s7a1lMm4grFoZBVsaZTKMHCZDs", "$type": "com.linkedin.voyager.identity.profile.ProfileView", "$deletedFields": ["summaryTreasuryMediaCount", "summaryTreasuryMedias", "entityLocale"], "testScoreView": "urn:li:fs_testScoreView:ACoAAACh6xgB8s7a1lMm4grFoZBVsaZTKMHCZDs", "volunteerCauseView": "urn:li:fs_volunteerCauseView:ACoAAACh6xgB8s7a1lMm4grFoZBVsaZTKMHCZDs", "entityUrn": "urn:li:fs_profileView:ACoAAACh6xgB8s7a1lMm4grFoZBVsaZTKMHCZDs", "courseView": "urn:li:fs_courseView:ACoAAACh6xgB8s7a1lMm4grFoZBVsaZTKMHCZDs", "honorView": "urn:li:fs_honorView:ACoAAACh6xgB8s7a1lMm4grFoZBVsaZTKMHCZDs", "skillView": "urn:li:fs_skillView:ACoAAACh6xgB8s7a1lMm4grFoZBVsaZTKMHCZDs", "volunteerExperienceView": "urn:li:fs_volunteerExperienceView:ACoAAACh6xgB8s7a1lMm4grFoZBVsaZTKMHCZDs", "primaryLocale": "urn:li:fs_profileView:ACoAAACh6xgB8s7a1lMm4grFoZBVsaZTKMHCZDs,primaryLocale", "publicationView": "urn:li:fs_publicationView:ACoAAACh6xgB8s7a1lMm4grFoZBVsaZTKMHCZDs"}, "included": [{"$deletedFields": ["day"], "month": 2, "year": 2007, "$type": "com.linkedin.common.Date", "$id": "urn:li:fs_position:(ACoAAACh6xgB8s7a1lMm4grFoZBVsaZTKMHCZDs,14500686),timePeriod,startDate"}, {"$deletedFields": [], "month": 11, "year": 2014, "day": 15, "$type": "com.linkedin.common.Date", "$id": "urn:li:fs_publication:(ACoAAACh6xgB8s7a1lMm4grFoZBVsaZTKMHCZDs,224),date"}, {"$deletedFields": ["day"], "month": 6, "year": 2014, "$type": "com.linkedin.common.Date", "$id": "urn:li:fs_position:(ACoAAACh6xgB8s7a1lMm4grFoZBVsaZTKMHCZDs,643247363),timePeriod,endDate"}, {"$deletedFields": ["day"], "month": 8, "year": 2017, "$type": "com.linkedin.common.Date", "$id": "urn:li:fs_position:(ACoAAACh6xgB8s7a1lMm4grFoZBVsaZTKMHCZDs,1139733168),timePeriod,startDate"}, {"$deletedFields": [], "month": 5, "year": 2017, "day": 16, "$type": "com.linkedin.common.Date", "$id": "urn:li:fs_publication:(ACoAAACh6xgB8s7a1lMm4grFoZBVsaZTKMHCZDs,300725221),date"}, {"$deletedFields": ["day"], "month": 2, "year": 2012, "$type": "com.linkedin.common.Date", "$id": "urn:li:fs_position:(ACoAAACh6xgB8s7a1lMm4grFoZBVsaZTKMHCZDs,14500686),timePeriod,endDate"}, {"$deletedFields": ["day"], "month": 7, "year": 2012, "$type": "com.linkedin.common.Date", "$id": "urn:li:fs_position:(ACoAAACh6xgB8s7a1lMm4grFoZBVsaZTKMHCZDs,643248594),timePeriod,startDate"}, {"$deletedFields": ["day"], "month": 6, "year": 2014, "$type": "com.linkedin.common.Date", "$id": "urn:li:fs_position:(ACoAAACh6xgB8s7a1lMm4grFoZBVsaZTKMHCZDs,643251424),timePeriod,startDate"}, {"$deletedFields": ["day"], "month": 11, "year": 2012, "$type": "com.linkedin.common.Date", "$id": "urn:li:fs_position:(ACoAAACh6xgB8s7a1lMm4grFoZBVsaZTKMHCZDs,643247363),timePeriod,startDate"}, {"$deletedFields": ["day"], "month": 10, "year": 2012, "$type": "com.linkedin.common.Date", "$id": "urn:li:fs_position:(ACoAAACh6xgB8s7a1lMm4grFoZBVsaZTKMHCZDs,643248594),timePeriod,endDate"}, {"country": "US", "$deletedFields": ["variant"], "language": "en", "$type": "com.linkedin.common.Locale", "$id": "urn:li:fs_profileView:ACoAAACh6xgB8s7a1lMm4grFoZBVsaZTKMHCZDs,primaryLocale"}, {"country": "US", "language": "en", "$deletedFields": ["variant"], "$type": "com.linkedin.common.Locale", "$id": "urn:li:fs_profile:ACoAAACh6xgB8s7a1lMm4grFoZBVsaZTKMHCZDs,supportedLocales,1204a34c-a6cf-4a96-a302-ef4fa907b34c-0"}, {"$deletedFields": [], "width": 200, "fileIdentifyingUrlPathSegment": "200_200/0?e=2123409600&v=beta&t=6NH1vnpwp19ud97ENO74x0Do3FsYE2IBsxIpbdhzXE8", "height": 200, "$type": "com.linkedin.common.VectorArtifact", "$id": "urn:li:fs_miniCompany:1033,logo,com.linkedin.common.VectorImage,artifacts,03900423-8542-46a6-8e4a-964d2545fe9c-0"}, {"$deletedFields": [], "width": 100, "fileIdentifyingUrlPathSegment": "100_100/0?e=2123409600&v=beta&t=fcY4VbKBLEbl_bQKMyT2WUTuPPh7c2BRsoU_3P3k9CM", "height": 100, "$type": "com.linkedin.common.VectorArtifact", "$id": "urn:li:fs_miniCompany:1033,logo,com.linkedin.common.VectorImage,artifacts,03900423-8542-46a6-8e4a-964d2545fe9c-1"}, {"$deletedFields": [], "width": 400, "fileIdentifyingUrlPathSegment": "400_400/0?e=2123409600&v=beta&t=jqsDX8mjBlM29rexYAinP_oJ67o86AiC8rb_JOCLevE", "height": 400, "$type": "com.linkedin.common.VectorArtifact", "$id": "urn:li:fs_miniCompany:1033,logo,com.linkedin.common.VectorImage,artifacts,03900423-8542-46a6-8e4a-964d2545fe9c-2"}, {"$deletedFields": [], "width": 200, "fileIdentifyingUrlPathSegment": "200_200/0?e=2123409600&v=beta&t=J051s9E9p8pW68N6Xy6udmZlWTPMaMkhm75Zkr-lAiI", "height": 200, "$type": "com.linkedin.common.VectorArtifact", "$id": "urn:li:fs_miniSchool:18633,logo,com.linkedin.common.VectorImage,artifacts,c3b50f8a-d91d-4dfc-89c9-3474a778d867-0"}, {"$deletedFields": [], "width": 800, "fileIdentifyingUrlPathSegment": "200_800/0?e=1529391600&v=beta&t=mlFFae04Xgi00Wi_-fMRa93jE_qHea7KVy9z-qOQenc", "height": 200, "$type": "com.linkedin.common.VectorArtifact", "$id": "urn:li:fs_miniProfile:ACoAAACh6xgB8s7a1lMm4grFoZBVsaZTKMHCZDs,backgroundImage,com.linkedin.common.VectorImage,artifacts,36874ac5-2f0a-4f51-9242-05334bb96fa8-0"}, {"$deletedFields": [], "width": 1400, "fileIdentifyingUrlPathSegment": "350_1400/0?e=1529391600&v=beta&t=5yMEaRWSaPAsworompnF59TzBKPzkIa1DxSRQCYsEYc", "height": 350, "$type": "com.linkedin.common.VectorArtifact", "$id": "urn:li:fs_miniProfile:ACoAAACh6xgB8s7a1lMm4grFoZBVsaZTKMHCZDs,backgroundImage,com.linkedin.common.VectorImage,artifacts,36874ac5-2f0a-4f51-9242-05334bb96fa8-1"}, {"$deletedFields": [], "width": 100, "fileIdentifyingUrlPathSegment": "100_100/0?e=2123409600&v=beta&t=x5iKJ6cvDh2q7eyL8uWxDXLCsWY-AC4wmJEKPAOj5X4", "height": 100, "$type": "com.linkedin.common.VectorArtifact", "$id": "urn:li:fs_miniSchool:18633,logo,com.linkedin.common.VectorImage,artifacts,c3b50f8a-d91d-4dfc-89c9-3474a778d867-1"}, {"$deletedFields": [], "width": 400, "fileIdentifyingUrlPathSegment": "400_400/0?e=2123409600&v=beta&t=yNE_ou0pjk8R0tiUIne0bon1zSAOW-xvLX3Fg7AFDJY", "height": 400, "$type": "com.linkedin.common.VectorArtifact", "$id": "urn:li:fs_miniSchool:18633,logo,com.linkedin.common.VectorImage,artifacts,c3b50f8a-d91d-4dfc-89c9-3474a778d867-2"}, {"$deletedFields": [], "width": 200, "fileIdentifyingUrlPathSegment": "200_200/0?e=2123409600&v=beta&t=i7n5h0Xc_irTPGP0kTx4RMVAhjoJaP78jFDuvxIANTo", "height": 200, "$type": "com.linkedin.common.VectorArtifact", "$id": "urn:li:fs_miniCompany:21837,logo,com.linkedin.common.VectorImage,artifacts,0f28fecf-65ae-43eb-8c25-3cce90a967f2-0"}, {"$deletedFields": [], "width": 400, "fileIdentifyingUrlPathSegment": "400_400/0?e=2123409600&v=beta&t=u8LtEpcrRwX0-wHkZNdVL4gdsPs-FbTRC3-wE2s3rNo", "height": 400, "$type": "com.linkedin.common.VectorArtifact", "$id": "urn:li:fs_miniCompany:21837,logo,com.linkedin.common.VectorImage,artifacts,0f28fecf-65ae-43eb-8c25-3cce90a967f2-2"}, {"$deletedFields": [], "width": 100, "fileIdentifyingUrlPathSegment": "100_100/0?e=2123409600&v=beta&t=Cl93wQaa2pdRlesHEMv4NtDG6g3KLo7lfIQcmCIcJvk", "height": 100, "$type": "com.linkedin.common.VectorArtifact", "$id": "urn:li:fs_miniCompany:21837,logo,com.linkedin.common.VectorImage,artifacts,0f28fecf-65ae-43eb-8c25-3cce90a967f2-1"}, {"$deletedFields": [], "width": 100, "fileIdentifyingUrlPathSegment": "100_100/0?e=1529391600&v=beta&t=1HXBpMUjES8HQCX4KrEvilTyXf1l588vxgXKePS89Hc", "height": 100, "$type": "com.linkedin.common.VectorArtifact", "$id": "urn:li:fs_miniProfile:ACoAAACh6xgB8s7a1lMm4grFoZBVsaZTKMHCZDs,picture,com.linkedin.common.VectorImage,artifacts,49c53d18-bffb-4f1d-82aa-17a549ad472d-0"}, {"$deletedFields": [], "width": 800, "fileIdentifyingUrlPathSegment": "800_800/0?e=1529391600&v=beta&t=crgTGhXtmXKq8LstA149T2-WNx1aRwn4cHLGYh11VUI", "height": 800, "$type": "com.linkedin.common.VectorArtifact", "$id": "urn:li:fs_miniProfile:ACoAAACh6xgB8s7a1lMm4grFoZBVsaZTKMHCZDs,picture,com.linkedin.common.VectorImage,artifacts,49c53d18-bffb-4f1d-82aa-17a549ad472d-3"}, {"$deletedFields": [], "width": 200, "fileIdentifyingUrlPathSegment": "200_200/0?e=1529391600&v=beta&t=QD_iJanokG8ceNUgDb6Iqlpnh8P65c2swI-9WU_or_0", "height": 200, "$type": "com.linkedin.common.VectorArtifact", "$id": "urn:li:fs_miniProfile:ACoAAACh6xgB8s7a1lMm4grFoZBVsaZTKMHCZDs,picture,com.linkedin.common.VectorImage,artifacts,49c53d18-bffb-4f1d-82aa-17a549ad472d-1"}, {"$deletedFields": [], "width": 400, "fileIdentifyingUrlPathSegment": "400_400/0?e=1529391600&v=beta&t=croaeWdJRBYnu4b6tHowYvUY38J8XRvoRSDBmXQBPLw", "height": 400, "$type": "com.linkedin.common.VectorArtifact", "$id": "urn:li:fs_miniProfile:ACoAAACh6xgB8s7a1lMm4grFoZBVsaZTKMHCZDs,picture,com.linkedin.common.VectorImage,artifacts,49c53d18-bffb-4f1d-82aa-17a549ad472d-2"}, {"$deletedFields": [], "width": 100, "fileIdentifyingUrlPathSegment": "100_100/0?e=2123409600&v=beta&t=6F67RsNFAgy5guEJGJjbYi97fUYR6XjPJ-6kD8cWNog", "height": 100, "$type": "com.linkedin.common.VectorArtifact", "$id": "urn:li:fs_miniSchool:18483,logo,com.linkedin.common.VectorImage,artifacts,bd222fc2-2026-4441-8954-5269eecfd413-1"}, {"$deletedFields": [], "width": 400, "fileIdentifyingUrlPathSegment": "400_400/0?e=2123409600&v=beta&t=pAuYkcgebTuspLQcQZdkr1Ag8m-cJNvPEryY5lVk3RA", "height": 400, "$type": "com.linkedin.common.VectorArtifact", "$id": "urn:li:fs_miniSchool:18483,logo,com.linkedin.common.VectorImage,artifacts,bd222fc2-2026-4441-8954-5269eecfd413-2"}, {"$deletedFields": [], "width": 200, "fileIdentifyingUrlPathSegment": "200_200/0?e=2123409600&v=beta&t=AcK1ajOlQX1SenclbJJKJMR5BzvTJQYuXsEXyEcywcY", "height": 200, "$type": "com.linkedin.common.VectorArtifact", "$id": "urn:li:fs_miniSchool:18483,logo,com.linkedin.common.VectorImage,artifacts,bd222fc2-2026-4441-8954-5269eecfd413-0"}, {"$deletedFields": [], "width": 400, "fileIdentifyingUrlPathSegment": "400_400/0?e=2123409600&v=beta&t=SHs0AE_Gwmx4YpV1b09OPuIkxgiJc0gJurNV1OLYFK4", "height": 400, "$type": "com.linkedin.common.VectorArtifact", "$id": "urn:li:fs_miniSchool:18946,logo,com.linkedin.common.VectorImage,artifacts,3c9589d3-64c0-4a4b-8ada-a3a654e983de-2"}, {"$deletedFields": [], "width": 200, "fileIdentifyingUrlPathSegment": "200_200/0?e=2123409600&v=beta&t=UwYLdoo-fVXCDVQdPCjTOf-J8hTmvHshs1_qxlZvQG8", "height": 200, "$type": "com.linkedin.common.VectorArtifact", "$id": "urn:li:fs_miniCompany:3805,logo,com.linkedin.common.VectorImage,artifacts,93572586-3cc8-4d62-b226-242ef1e04dc4-0"}, {"$deletedFields": [], "width": 200, "fileIdentifyingUrlPathSegment": "200_200/0?e=2123409600&v=beta&t=WXt57OfO76cV7KGbmE7gubKnnHwiwI5mCrDgH1x5g7g", "height": 200, "$type": "com.linkedin.common.VectorArtifact", "$id": "urn:li:fs_miniSchool:18946,logo,com.linkedin.common.VectorImage,artifacts,3c9589d3-64c0-4a4b-8ada-a3a654e983de-0"}, {"$deletedFields": [], "width": 100, "fileIdentifyingUrlPathSegment": "100_100/0?e=2123409600&v=beta&t=QY3TwOxBP_4h0-r6qM6hR4Wck3MIhAb4nIiRV7vziL0", "height": 100, "$type": "com.linkedin.common.VectorArtifact", "$id": "urn:li:fs_miniSchool:18946,logo,com.linkedin.common.VectorImage,artifacts,3c9589d3-64c0-4a4b-8ada-a3a654e983de-1"}, {"$deletedFields": [], "width": 1400, "fileIdentifyingUrlPathSegment": "350_1400/0?e=1529391600&v=beta&t=5yMEaRWSaPAsworompnF59TzBKPzkIa1DxSRQCYsEYc", "height": 350, "$type": "com.linkedin.common.VectorArtifact", "$id": "urn:li:fs_miniProfile:ACoAAACh6xgB8s7a1lMm4grFoZBVsaZTKMHCZDs,backgroundImage,com.linkedin.common.VectorImage,artifacts,c115e8a8-4394-42f3-a731-93be9c7f9044-1"}, {"$deletedFields": [], "width": 800, "fileIdentifyingUrlPathSegment": "200_800/0?e=1529391600&v=beta&t=mlFFae04Xgi00Wi_-fMRa93jE_qHea7KVy9z-qOQenc", "height": 200, "$type": "com.linkedin.common.VectorArtifact", "$id": "urn:li:fs_miniProfile:ACoAAACh6xgB8s7a1lMm4grFoZBVsaZTKMHCZDs,backgroundImage,com.linkedin.common.VectorImage,artifacts,c115e8a8-4394-42f3-a731-93be9c7f9044-0"}, {"$deletedFields": [], "width": 400, "fileIdentifyingUrlPathSegment": "400_400/0?e=2123409600&v=beta&t=OjKvGgq30O5SrEa5LyQYnsvp0GmqZgj5iF_d89exApA", "height": 400, "$type": "com.linkedin.common.VectorArtifact", "$id": "urn:li:fs_miniCompany:3805,logo,com.linkedin.common.VectorImage,artifacts,93572586-3cc8-4d62-b226-242ef1e04dc4-2"}, {"$deletedFields": [], "width": 100, "fileIdentifyingUrlPathSegment": "100_100/0?e=2123409600&v=beta&t=NaVx0Ca0P2OI7AKKSD9FMw5Q7F95XRvylCckN3uIRuQ", "height": 100, "$type": "com.linkedin.common.VectorArtifact", "$id": "urn:li:fs_miniCompany:3805,logo,com.linkedin.common.VectorImage,artifacts,93572586-3cc8-4d62-b226-242ef1e04dc4-1"}, {"$deletedFields": [], "width": 800, "fileIdentifyingUrlPathSegment": "800_800/0?e=1529391600&v=beta&t=crgTGhXtmXKq8LstA149T2-WNx1aRwn4cHLGYh11VUI", "height": 800, "$type": "com.linkedin.common.VectorArtifact", "$id": "urn:li:fs_miniProfile:ACoAAACh6xgB8s7a1lMm4grFoZBVsaZTKMHCZDs,picture,com.linkedin.common.VectorImage,artifacts,b8e75248-621c-4309-9d92-7495b3bac546-3"}, {"$deletedFields": [], "width": 400, "fileIdentifyingUrlPathSegment": "400_400/0?e=1529391600&v=beta&t=croaeWdJRBYnu4b6tHowYvUY38J8XRvoRSDBmXQBPLw", "height": 400, "$type": "com.linkedin.common.VectorArtifact", "$id": "urn:li:fs_miniProfile:ACoAAACh6xgB8s7a1lMm4grFoZBVsaZTKMHCZDs,picture,com.linkedin.common.VectorImage,artifacts,b8e75248-621c-4309-9d92-7495b3bac546-2"}, {"$deletedFields": [], "width": 800, "fileIdentifyingUrlPathSegment": "200_800/0?e=1529391600&v=beta&t=mlFFae04Xgi00Wi_-fMRa93jE_qHea7KVy9z-qOQenc", "height": 200, "$type": "com.linkedin.common.VectorArtifact", "$id": "urn:li:fs_miniProfile:ACoAAACh6xgB8s7a1lMm4grFoZBVsaZTKMHCZDs,backgroundImage,com.linkedin.common.VectorImage,artifacts,da00ef7f-9699-4c9d-b580-2eb7e5f94084-0"}, {"$deletedFields": [], "width": 1400, "fileIdentifyingUrlPathSegment": "350_1400/0?e=1529391600&v=beta&t=5yMEaRWSaPAsworompnF59TzBKPzkIa1DxSRQCYsEYc", "height": 350, "$type": "com.linkedin.common.VectorArtifact", "$id": "urn:li:fs_miniProfile:ACoAAACh6xgB8s7a1lMm4grFoZBVsaZTKMHCZDs,backgroundImage,com.linkedin.common.VectorImage,artifacts,da00ef7f-9699-4c9d-b580-2eb7e5f94084-1"}, {"$deletedFields": [], "width": 200, "fileIdentifyingUrlPathSegment": "200_200/0?e=1529391600&v=beta&t=QD_iJanokG8ceNUgDb6Iqlpnh8P65c2swI-9WU_or_0", "height": 200, "$type": "com.linkedin.common.VectorArtifact", "$id": "urn:li:fs_miniProfile:ACoAAACh6xgB8s7a1lMm4grFoZBVsaZTKMHCZDs,picture,com.linkedin.common.VectorImage,artifacts,b8e75248-621c-4309-9d92-7495b3bac546-1"}, {"$deletedFields": [], "width": 100, "fileIdentifyingUrlPathSegment": "100_100/0?e=1529391600&v=beta&t=1HXBpMUjES8HQCX4KrEvilTyXf1l588vxgXKePS89Hc", "height": 100, "$type": "com.linkedin.common.VectorArtifact", "$id": "urn:li:fs_miniProfile:ACoAAACh6xgB8s7a1lMm4grFoZBVsaZTKMHCZDs,picture,com.linkedin.common.VectorImage,artifacts,b8e75248-621c-4309-9d92-7495b3bac546-0"}, {"$deletedFields": [], "width": 100, "fileIdentifyingUrlPathSegment": "100_100/0?e=2123409600&v=beta&t=uFRA5HCxAu-PvUyhYXyHJp9Fx4Wv14a_92fMWDP6PWw", "height": 100, "$type": "com.linkedin.common.VectorArtifact", "$id": "urn:li:fs_miniCompany:1459397,logo,com.linkedin.common.VectorImage,artifacts,f347cfd3-40a9-495c-a729-4972e42e4155-1"}, {"$deletedFields": [], "width": 200, "fileIdentifyingUrlPathSegment": "200_200/0?e=2123409600&v=beta&t=t3fr5-3KvJZxT9J07PagH0jokFh7n2PcQGDTJG-A7AE", "height": 200, "$type": "com.linkedin.common.VectorArtifact", "$id": "urn:li:fs_miniCompany:1459397,logo,com.linkedin.common.VectorImage,artifacts,f347cfd3-40a9-495c-a729-4972e42e4155-0"}, {"$deletedFields": [], "width": 200, "fileIdentifyingUrlPathSegment": "200_200/0?e=1529391600&v=beta&t=QD_iJanokG8ceNUgDb6Iqlpnh8P65c2swI-9WU_or_0", "height": 200, "$type": "com.linkedin.common.VectorArtifact", "$id": "urn:li:fs_miniProfile:ACoAAACh6xgB8s7a1lMm4grFoZBVsaZTKMHCZDs,picture,com.linkedin.common.VectorImage,artifacts,38daab13-1f9c-4634-a211-cb7dbfd6546c-1"}, {"$deletedFields": [], "width": 100, "fileIdentifyingUrlPathSegment": "100_100/0?e=1529391600&v=beta&t=1HXBpMUjES8HQCX4KrEvilTyXf1l588vxgXKePS89Hc", "height": 100, "$type": "com.linkedin.common.VectorArtifact", "$id": "urn:li:fs_miniProfile:ACoAAACh6xgB8s7a1lMm4grFoZBVsaZTKMHCZDs,picture,com.linkedin.common.VectorImage,artifacts,38daab13-1f9c-4634-a211-cb7dbfd6546c-0"}, {"$deletedFields": [], "width": 800, "fileIdentifyingUrlPathSegment": "800_800/0?e=1529391600&v=beta&t=crgTGhXtmXKq8LstA149T2-WNx1aRwn4cHLGYh11VUI", "height": 800, "$type": "com.linkedin.common.VectorArtifact", "$id": "urn:li:fs_miniProfile:ACoAAACh6xgB8s7a1lMm4grFoZBVsaZTKMHCZDs,picture,com.linkedin.common.VectorImage,artifacts,38daab13-1f9c-4634-a211-cb7dbfd6546c-3"}, {"$deletedFields": [], "width": 400, "fileIdentifyingUrlPathSegment": "400_400/0?e=2123409600&v=beta&t=ypn4duLr8AEw5qV7f-9itjyn7W3Fls3l6axyjNO74yQ", "height": 400, "$type": "com.linkedin.common.VectorArtifact", "$id": "urn:li:fs_miniCompany:1459397,logo,com.linkedin.common.VectorImage,artifacts,f347cfd3-40a9-495c-a729-4972e42e4155-2"}, {"$deletedFields": [], "width": 400, "fileIdentifyingUrlPathSegment": "400_400/0?e=1529391600&v=beta&t=croaeWdJRBYnu4b6tHowYvUY38J8XRvoRSDBmXQBPLw", "height": 400, "$type": "com.linkedin.common.VectorArtifact", "$id": "urn:li:fs_miniProfile:ACoAAACh6xgB8s7a1lMm4grFoZBVsaZTKMHCZDs,picture,com.linkedin.common.VectorImage,artifacts,38daab13-1f9c-4634-a211-cb7dbfd6546c-2"}, {"$deletedFields": ["attribution"], "artifacts": ["urn:li:fs_miniCompany:21837,logo,com.linkedin.common.VectorImage,artifacts,0f28fecf-65ae-43eb-8c25-3cce90a967f2-0", "urn:li:fs_miniCompany:21837,logo,com.linkedin.common.VectorImage,artifacts,0f28fecf-65ae-43eb-8c25-3cce90a967f2-1", "urn:li:fs_miniCompany:21837,logo,com.linkedin.common.VectorImage,artifacts,0f28fecf-65ae-43eb-8c25-3cce90a967f2-2"], "rootUrl": "https://media.licdn.com/dms/image/C4E0BAQEV2tR4taOftg/company-logo_", "$type": "com.linkedin.common.VectorImage", "$id": "urn:li:fs_miniCompany:21837,logo,com.linkedin.common.VectorImage"}, {"$deletedFields": ["attribution"], "artifacts": ["urn:li:fs_miniCompany:1033,logo,com.linkedin.common.VectorImage,artifacts,03900423-8542-46a6-8e4a-964d2545fe9c-0", "urn:li:fs_miniCompany:1033,logo,com.linkedin.common.VectorImage,artifacts,03900423-8542-46a6-8e4a-964d2545fe9c-1", "urn:li:fs_miniCompany:1033,logo,com.linkedin.common.VectorImage,artifacts,03900423-8542-46a6-8e4a-964d2545fe9c-2"], "rootUrl": "https://media.licdn.com/dms/image/C4D0BAQELp2gfntieXg/company-logo_", "$type": "com.linkedin.common.VectorImage", "$id": "urn:li:fs_miniCompany:1033,logo,com.linkedin.common.VectorImage"}, {"$deletedFields": ["attribution"], "artifacts": ["urn:li:fs_miniProfile:ACoAAACh6xgB8s7a1lMm4grFoZBVsaZTKMHCZDs,backgroundImage,com.linkedin.common.VectorImage,artifacts,da00ef7f-9699-4c9d-b580-2eb7e5f94084-0", "urn:li:fs_miniProfile:ACoAAACh6xgB8s7a1lMm4grFoZBVsaZTKMHCZDs,backgroundImage,com.linkedin.common.VectorImage,artifacts,da00ef7f-9699-4c9d-b580-2eb7e5f94084-1"], "rootUrl": "https://media.licdn.com/dms/image/C4E16AQH-4a91H7SPww/profile-displaybackgroundimage-shrink_", "$type": "com.linkedin.common.VectorImage", "$id": "urn:li:fs_miniProfile:ACoAAACh6xgB8s7a1lMm4grFoZBVsaZTKMHCZDs,backgroundImage,com.linkedin.common.VectorImage"}, {"$deletedFields": ["attribution"], "artifacts": ["urn:li:fs_miniSchool:18483,logo,com.linkedin.common.VectorImage,artifacts,bd222fc2-2026-4441-8954-5269eecfd413-0", "urn:li:fs_miniSchool:18483,logo,com.linkedin.common.VectorImage,artifacts,bd222fc2-2026-4441-8954-5269eecfd413-1", "urn:li:fs_miniSchool:18483,logo,com.linkedin.common.VectorImage,artifacts,bd222fc2-2026-4441-8954-5269eecfd413-2"], "rootUrl": "https://media.licdn.com/dms/image/C4E0BAQF5t62bcL0e9g/company-logo_", "$type": "com.linkedin.common.VectorImage", "$id": "urn:li:fs_miniSchool:18483,logo,com.linkedin.common.VectorImage"}, {"$deletedFields": ["attribution"], "artifacts": ["urn:li:fs_miniCompany:3805,logo,com.linkedin.common.VectorImage,artifacts,93572586-3cc8-4d62-b226-242ef1e04dc4-0", "urn:li:fs_miniCompany:3805,logo,com.linkedin.common.VectorImage,artifacts,93572586-3cc8-4d62-b226-242ef1e04dc4-1", "urn:li:fs_miniCompany:3805,logo,com.linkedin.common.VectorImage,artifacts,93572586-3cc8-4d62-b226-242ef1e04dc4-2"], "rootUrl": "https://media.licdn.com/dms/image/C4D0BAQEh4m3OQ70slw/company-logo_", "$type": "com.linkedin.common.VectorImage", "$id": "urn:li:fs_miniCompany:3805,logo,com.linkedin.common.VectorImage"}, {"$deletedFields": ["attribution"], "artifacts": ["urn:li:fs_miniSchool:18633,logo,com.linkedin.common.VectorImage,artifacts,c3b50f8a-d91d-4dfc-89c9-3474a778d867-0", "urn:li:fs_miniSchool:18633,logo,com.linkedin.common.VectorImage,artifacts,c3b50f8a-d91d-4dfc-89c9-3474a778d867-1", "urn:li:fs_miniSchool:18633,logo,com.linkedin.common.VectorImage,artifacts,c3b50f8a-d91d-4dfc-89c9-3474a778d867-2"], "rootUrl": "https://media.licdn.com/dms/image/C4E0BAQFGfERBPGurCg/company-logo_", "$type": "com.linkedin.common.VectorImage", "$id": "urn:li:fs_miniSchool:18633,logo,com.linkedin.common.VectorImage"}, {"$deletedFields": ["attribution"], "artifacts": ["urn:li:fs_miniSchool:18946,logo,com.linkedin.common.VectorImage,artifacts,3c9589d3-64c0-4a4b-8ada-a3a654e983de-0", "urn:li:fs_miniSchool:18946,logo,com.linkedin.common.VectorImage,artifacts,3c9589d3-64c0-4a4b-8ada-a3a654e983de-1", "urn:li:fs_miniSchool:18946,logo,com.linkedin.common.VectorImage,artifacts,3c9589d3-64c0-4a4b-8ada-a3a654e983de-2"], "rootUrl": "https://media.licdn.com/dms/image/C560BAQE8SOXGRyv7LA/company-logo_", "$type": "com.linkedin.common.VectorImage", "$id": "urn:li:fs_miniSchool:18946,logo,com.linkedin.common.VectorImage"}, {"$deletedFields": ["attribution"], "artifacts": ["urn:li:fs_miniCompany:1459397,logo,com.linkedin.common.VectorImage,artifacts,f347cfd3-40a9-495c-a729-4972e42e4155-0", "urn:li:fs_miniCompany:1459397,logo,com.linkedin.common.VectorImage,artifacts,f347cfd3-40a9-495c-a729-4972e42e4155-1", "urn:li:fs_miniCompany:1459397,logo,com.linkedin.common.VectorImage,artifacts,f347cfd3-40a9-495c-a729-4972e42e4155-2"], "rootUrl": "https://media.licdn.com/dms/image/C560BAQErNJwYgYmzxw/company-logo_", "$type": "com.linkedin.common.VectorImage", "$id": "urn:li:fs_miniCompany:1459397,logo,com.linkedin.common.VectorImage"}, {"$deletedFields": ["attribution"], "artifacts": ["urn:li:fs_miniProfile:ACoAAACh6xgB8s7a1lMm4grFoZBVsaZTKMHCZDs,picture,com.linkedin.common.VectorImage,artifacts,49c53d18-bffb-4f1d-82aa-17a549ad472d-0", "urn:li:fs_miniProfile:ACoAAACh6xgB8s7a1lMm4grFoZBVsaZTKMHCZDs,picture,com.linkedin.common.VectorImage,artifacts,49c53d18-bffb-4f1d-82aa-17a549ad472d-1", "urn:li:fs_miniProfile:ACoAAACh6xgB8s7a1lMm4grFoZBVsaZTKMHCZDs,picture,com.linkedin.common.VectorImage,artifacts,49c53d18-bffb-4f1d-82aa-17a549ad472d-2", "urn:li:fs_miniProfile:ACoAAACh6xgB8s7a1lMm4grFoZBVsaZTKMHCZDs,picture,com.linkedin.common.VectorImage,artifacts,49c53d18-bffb-4f1d-82aa-17a549ad472d-3"], "rootUrl": "https://media.licdn.com/dms/image/C4E03AQHDBA15ReOy4Q/profile-displayphoto-shrink_", "$type": "com.linkedin.common.VectorImage", "$id": "urn:li:fs_miniProfile:ACoAAACh6xgB8s7a1lMm4grFoZBVsaZTKMHCZDs,picture,com.linkedin.common.VectorImage"}, {"total": 0, "$deletedFields": [], "start": 0, "count": 10, "links": [], "$type": "com.linkedin.restli.common.CollectionMetadata", "$id": "urn:li:fs_patentView:ACoAAACh6xgB8s7a1lMm4grFoZBVsaZTKMHCZDs,paging"}, {"total": 0, "$deletedFields": [], "start": 0, "count": 0, "links": [], "$type": "com.linkedin.restli.common.CollectionMetadata", "$id": "urn:li:fs_volunteerCauseView:ACoAAACh6xgB8s7a1lMm4grFoZBVsaZTKMHCZDs,paging"}, {"total": 3, "$deletedFields": [], "start": 0, "count": 3, "links": [], "$type": "com.linkedin.restli.common.CollectionMetadata", "$id": "urn:li:fs_educationView:ACoAAACh6xgB8s7a1lMm4grFoZBVsaZTKMHCZDs,paging"}, {"total": 0, "$deletedFields": [], "start": 0, "count": 10, "links": [], "$type": "com.linkedin.restli.common.CollectionMetadata", "$id": "urn:li:fs_languageView:ACoAAACh6xgB8s7a1lMm4grFoZBVsaZTKMHCZDs,paging"}, {"total": 0, "$deletedFields": [], "start": 0, "count": 10, "links": [], "$type": "com.linkedin.restli.common.CollectionMetadata", "$id": "urn:li:fs_projectView:ACoAAACh6xgB8s7a1lMm4grFoZBVsaZTKMHCZDs,paging"}, {"total": 0, "$deletedFields": [], "start": 0, "count": 10, "links": [], "$type": "com.linkedin.restli.common.CollectionMetadata", "$id": "urn:li:fs_certificationView:ACoAAACh6xgB8s7a1lMm4grFoZBVsaZTKMHCZDs,paging"}, {"total": 0, "$deletedFields": [], "start": 0, "count": 10, "links": [], "$type": "com.linkedin.restli.common.CollectionMetadata", "$id": "urn:li:fs_organizationView:ACoAAACh6xgB8s7a1lMm4grFoZBVsaZTKMHCZDs,paging"}, {"total": 33, "$deletedFields": [], "start": 0, "count": 4, "links": [], "$type": "com.linkedin.restli.common.CollectionMetadata", "$id": "urn:li:fs_skillView:ACoAAACh6xgB8s7a1lMm4grFoZBVsaZTKMHCZDs,paging"}, {"total": 0, "$deletedFields": [], "start": 0, "count": 3, "links": [], "$type": "com.linkedin.restli.common.CollectionMetadata", "$id": "urn:li:fs_volunteerExperienceView:ACoAAACh6xgB8s7a1lMm4grFoZBVsaZTKMHCZDs,paging"}, {"total": 0, "$deletedFields": [], "start": 0, "count": 10, "links": [], "$type": "com.linkedin.restli.common.CollectionMetadata", "$id": "urn:li:fs_courseView:ACoAAACh6xgB8s7a1lMm4grFoZBVsaZTKMHCZDs,paging"}, {"total": 0, "$deletedFields": [], "start": 0, "count": 10, "links": [], "$type": "com.linkedin.restli.common.CollectionMetadata", "$id": "urn:li:fs_testScoreView:ACoAAACh6xgB8s7a1lMm4grFoZBVsaZTKMHCZDs,paging"}, {"total": 2, "$deletedFields": [], "start": 0, "count": 10, "links": [], "$type": "com.linkedin.restli.common.CollectionMetadata", "$id": "urn:li:fs_publicationView:ACoAAACh6xgB8s7a1lMm4grFoZBVsaZTKMHCZDs,paging"}, {"total": 7, "$deletedFields": [], "start": 0, "count": 5, "links": [], "$type": "com.linkedin.restli.common.CollectionMetadata", "$id": "urn:li:fs_positionView:ACoAAACh6xgB8s7a1lMm4grFoZBVsaZTKMHCZDs,paging"}, {"total": 0, "$deletedFields": [], "start": 0, "count": 10, "links": [], "$type": "com.linkedin.restli.common.CollectionMetadata", "$id": "urn:li:fs_honorView:ACoAAACh6xgB8s7a1lMm4grFoZBVsaZTKMHCZDs,paging"}, {"$deletedFields": ["endDate"], "startDate": "urn:li:fs_position:(ACoAAACh6xgB8s7a1lMm4grFoZBVsaZTKMHCZDs,1139733168),timePeriod,startDate", "$type": "com.linkedin.voyager.common.DateRange", "$id": "urn:li:fs_position:(ACoAAACh6xgB8s7a1lMm4grFoZBVsaZTKMHCZDs,1139733168),timePeriod"}, {"$deletedFields": ["endDate"], "startDate": "urn:li:fs_position:(ACoAAACh6xgB8s7a1lMm4grFoZBVsaZTKMHCZDs,643251424),timePeriod,startDate", "$type": "com.linkedin.voyager.common.DateRange", "$id": "urn:li:fs_position:(ACoAAACh6xgB8s7a1lMm4grFoZBVsaZTKMHCZDs,643251424),timePeriod"}, {"$deletedFields": [], "endDate": "urn:li:fs_position:(ACoAAACh6xgB8s7a1lMm4grFoZBVsaZTKMHCZDs,643248594),timePeriod,endDate", "startDate": "urn:li:fs_position:(ACoAAACh6xgB8s7a1lMm4grFoZBVsaZTKMHCZDs,643248594),timePeriod,startDate", "$type": "com.linkedin.voyager.common.DateRange", "$id": "urn:li:fs_position:(ACoAAACh6xgB8s7a1lMm4grFoZBVsaZTKMHCZDs,643248594),timePeriod"}, {"$deletedFields": [], "endDate": "urn:li:fs_position:(ACoAAACh6xgB8s7a1lMm4grFoZBVsaZTKMHCZDs,643247363),timePeriod,endDate", "startDate": "urn:li:fs_position:(ACoAAACh6xgB8s7a1lMm4grFoZBVsaZTKMHCZDs,643247363),timePeriod,startDate", "$type": "com.linkedin.voyager.common.DateRange", "$id": "urn:li:fs_position:(ACoAAACh6xgB8s7a1lMm4grFoZBVsaZTKMHCZDs,643247363),timePeriod"}, {"$deletedFields": [], "endDate": "urn:li:fs_position:(ACoAAACh6xgB8s7a1lMm4grFoZBVsaZTKMHCZDs,14500686),timePeriod,endDate", "startDate": "urn:li:fs_position:(ACoAAACh6xgB8s7a1lMm4grFoZBVsaZTKMHCZDs,14500686),timePeriod,startDate", "$type": "com.linkedin.voyager.common.DateRange", "$id": "urn:li:fs_position:(ACoAAACh6xgB8s7a1lMm4grFoZBVsaZTKMHCZDs,14500686),timePeriod"}, {"$deletedFields": [], "countryCode": "us", "postalCode": "75063", "$type": "com.linkedin.voyager.common.NormBasicLocation", "$id": "urn:li:fs_profile:ACoAAACh6xgB8s7a1lMm4grFoZBVsaZTKMHCZDs,location,basicLocation"}, {"$deletedFields": ["universalName"], "objectUrn": "urn:li:company:1033", "entityUrn": "urn:li:fs_miniCompany:1033", "name": "Accenture", "showcase": false, "active": true, "logo": {"com.linkedin.common.VectorImage": "urn:li:fs_miniCompany:1033,logo,com.linkedin.common.VectorImage"}, "trackingId": "LpmEj+JuQkGGIxT6b5Ygnw==", "$type": "com.linkedin.voyager.entities.shared.MiniCompany"}, {"$deletedFields": ["universalName"], "objectUrn": "urn:li:company:1459397", "entityUrn": "urn:li:fs_miniCompany:1459397", "name": "tekzenit, Inc.", "showcase": false, "active": true, "logo": {"com.linkedin.common.VectorImage": "urn:li:fs_miniCompany:1459397,logo,com.linkedin.common.VectorImage"}, "trackingId": "vIFKt30MR1qMAf8Kr+80lQ==", "$type": "com.linkedin.voyager.entities.shared.MiniCompany"}, {"$deletedFields": ["universalName"], "objectUrn": "urn:li:company:21837", "entityUrn": "urn:li:fs_miniCompany:21837", "name": "Credera", "showcase": false, "active": true, "logo": {"com.linkedin.common.VectorImage": "urn:li:fs_miniCompany:21837,logo,com.linkedin.common.VectorImage"}, "trackingId": "D0sqKKLOS0WmF6WiINjfCA==", "$type": "com.linkedin.voyager.entities.shared.MiniCompany"}, {"$deletedFields": ["universalName"], "objectUrn": "urn:li:company:3805", "entityUrn": "urn:li:fs_miniCompany:3805", "name": "WebEx", "showcase": false, "active": true, "logo": {"com.linkedin.common.VectorImage": "urn:li:fs_miniCompany:3805,logo,com.linkedin.common.VectorImage"}, "trackingId": "UsXNxjtCTfmfYneatzUyFQ==", "$type": "com.linkedin.voyager.entities.shared.MiniCompany"}, {"$deletedFields": [], "objectUrn": "urn:li:school:18946", "entityUrn": "urn:li:fs_miniSchool:18946", "active": true, "logo": {"com.linkedin.common.VectorImage": "urn:li:fs_miniSchool:18946,logo,com.linkedin.common.VectorImage"}, "schoolName": "Cornell University", "trackingId": "xIa/jQ22SGS8E+xQQQz+dw==", "$type": "com.linkedin.voyager.entities.shared.MiniSchool"}, {"$deletedFields": [], "objectUrn": "urn:li:school:18483", "entityUrn": "urn:li:fs_miniSchool:18483", "active": true, "logo": {"com.linkedin.common.VectorImage": "urn:li:fs_miniSchool:18483,logo,com.linkedin.common.VectorImage"}, "schoolName": "Harvard University", "trackingId": "coH3nhNZQoOthpwC5p2qVA==", "$type": "com.linkedin.voyager.entities.shared.MiniSchool"}, {"$deletedFields": [], "objectUrn": "urn:li:school:18633", "entityUrn": "urn:li:fs_miniSchool:18633", "active": true, "logo": {"com.linkedin.common.VectorImage": "urn:li:fs_miniSchool:18633,logo,com.linkedin.common.VectorImage"}, "schoolName": "University of Michigan", "trackingId": "EWtUf0d/QYKJEFAdxmKBag==", "$type": "com.linkedin.voyager.entities.shared.MiniSchool"}, {"$deletedFields": [], "entityUrn": "urn:li:fs_certificationView:ACoAAACh6xgB8s7a1lMm4grFoZBVsaZTKMHCZDs", "profileId": "ACoAAACh6xgB8s7a1lMm4grFoZBVsaZTKMHCZDs", "elements": [], "paging": "urn:li:fs_certificationView:ACoAAACh6xgB8s7a1lMm4grFoZBVsaZTKMHCZDs,paging", "$type": "com.linkedin.voyager.identity.profile.CertificationView"}, {"$deletedFields": ["name"], "entityUrn": "urn:li:fs_contributor:(ACoAAACh6xgB8s7a1lMm4grFoZBVsaZTKMHCZDs,300725221,140185630)", "member": "urn:li:fs_miniProfile:ACoAAACh6xgB8s7a1lMm4grFoZBVsaZTKMHCZDs", "profileUrn": "urn:li:fs_miniProfile:ACoAAACh6xgB8s7a1lMm4grFoZBVsaZTKMHCZDs", "$type": "com.linkedin.voyager.identity.profile.Contributor"}, {"$deletedFields": ["name"], "entityUrn": "urn:li:fs_contributor:(ACoAAACh6xgB8s7a1lMm4grFoZBVsaZTKMHCZDs,224,225)", "member": "urn:li:fs_miniProfile:ACoAAACh6xgB8s7a1lMm4grFoZBVsaZTKMHCZDs", "profileUrn": "urn:li:fs_miniProfile:ACoAAACh6xgB8s7a1lMm4grFoZBVsaZTKMHCZDs", "$type": "com.linkedin.voyager.identity.profile.Contributor"}, {"$deletedFields": [], "entityUrn": "urn:li:fs_courseView:ACoAAACh6xgB8s7a1lMm4grFoZBVsaZTKMHCZDs", "profileId": "ACoAAACh6xgB8s7a1lMm4grFoZBVsaZTKMHCZDs", "elements": [], "paging": "urn:li:fs_courseView:ACoAAACh6xgB8s7a1lMm4grFoZBVsaZTKMHCZDs,paging", "$type": "com.linkedin.voyager.identity.profile.CourseView"}, {"$deletedFields": ["courses", "projects", "recommendations", "honors", "entityLocale", "activities", "grade", "timePeriod", "fieldOfStudyUrn", "testScores", "fieldOfStudy", "degreeUrn"], "entityUrn": "urn:li:fs_education:(ACoAAACh6xgB8s7a1lMm4grFoZBVsaZTKMHCZDs,275359378)", "school": "urn:li:fs_miniSchool:18946", "description": "Capstone Project: Create a product strategy for restaurant-aggregator meal delivery service", "degreeName": "Customer-Focused Product and Service Design", "schoolName": "Cornell University", "schoolUrn": "urn:li:fs_miniSchool:18946", "$type": "com.linkedin.voyager.identity.profile.Education"}, {"$deletedFields": ["courses", "projects", "description", "recommendations", "honors", "entityLocale", "grade", "timePeriod", "testScores", "fieldOfStudy", "degreeUrn"], "entityUrn": "urn:li:fs_education:(ACoAAACh6xgB8s7a1lMm4grFoZBVsaZTKMHCZDs,6950457)", "school": "urn:li:fs_miniSchool:18633", "activities": "Elected College Senator for Student Government", "fieldOfStudyUrn": "urn:li:fs_fieldOfStudy:100608", "degreeName": "Bachelor of Science (B.S.)", "schoolName": "University of Michigan", "schoolUrn": "urn:li:fs_miniSchool:18633", "$type": "com.linkedin.voyager.identity.profile.Education"}, {"$deletedFields": ["courses", "projects", "recommendations", "honors", "entityLocale", "activities", "grade", "timePeriod", "fieldOfStudyUrn", "testScores"], "entityUrn": "urn:li:fs_education:(ACoAAACh6xgB8s7a1lMm4grFoZBVsaZTKMHCZDs,512311948)", "school": "urn:li:fs_miniSchool:18483", "description": "Degree in progress.  Completed one-third of the program.\n\nProgram Overview:\nDevelop an understanding and application of the latest tools in the communication portfolio, such as web design, video, and still photography.  Build deeper knowledge of modern production methods and perspective to harness new and emerging technologies.", "degreeName": "Master's degree", "schoolName": "Harvard University", "fieldOfStudy": "Digital Media Design", "degreeUrn": "urn:li:fs_degree:500", "schoolUrn": "urn:li:fs_miniSchool:18483", "$type": "com.linkedin.voyager.identity.profile.Education"}, {"$deletedFields": [], "entityUrn": "urn:li:fs_educationView:ACoAAACh6xgB8s7a1lMm4grFoZBVsaZTKMHCZDs", "profileId": "ACoAAACh6xgB8s7a1lMm4grFoZBVsaZTKMHCZDs", "elements": ["urn:li:fs_education:(ACoAAACh6xgB8s7a1lMm4grFoZBVsaZTKMHCZDs,512311948)", "urn:li:fs_education:(ACoAAACh6xgB8s7a1lMm4grFoZBVsaZTKMHCZDs,275359378)", "urn:li:fs_education:(ACoAAACh6xgB8s7a1lMm4grFoZBVsaZTKMHCZDs,6950457)"], "paging": "urn:li:fs_educationView:ACoAAACh6xgB8s7a1lMm4grFoZBVsaZTKMHCZDs,paging", "$type": "com.linkedin.voyager.identity.profile.EducationView"}, {"$deletedFields": [], "start": 51, "end": 200, "$type": "com.linkedin.voyager.identity.profile.EmployeeCountRange", "$id": "urn:li:fs_position:(ACoAAACh6xgB8s7a1lMm4grFoZBVsaZTKMHCZDs,643247363),company,employeeCountRange"}, {"$deletedFields": ["end"], "start": 10001, "$type": "com.linkedin.voyager.identity.profile.EmployeeCountRange", "$id": "urn:li:fs_position:(ACoAAACh6xgB8s7a1lMm4grFoZBVsaZTKMHCZDs,14500686),company,employeeCountRange"}, {"$deletedFields": [], "start": 201, "end": 500, "$type": "com.linkedin.voyager.identity.profile.EmployeeCountRange", "$id": "urn:li:fs_position:(ACoAAACh6xgB8s7a1lMm4grFoZBVsaZTKMHCZDs,643248594),company,employeeCountRange"}, {"$deletedFields": ["end"], "start": 10001, "$type": "com.linkedin.voyager.identity.profile.EmployeeCountRange", "$id": "urn:li:fs_position:(ACoAAACh6xgB8s7a1lMm4grFoZBVsaZTKMHCZDs,643251424),company,employeeCountRange"}, {"$deletedFields": [], "entityUrn": "urn:li:fs_honorView:ACoAAACh6xgB8s7a1lMm4grFoZBVsaZTKMHCZDs", "profileId": "ACoAAACh6xgB8s7a1lMm4grFoZBVsaZTKMHCZDs", "elements": [], "paging": "urn:li:fs_honorView:ACoAAACh6xgB8s7a1lMm4grFoZBVsaZTKMHCZDs,paging", "$type": "com.linkedin.voyager.identity.profile.HonorView"}, {"$deletedFields": [], "entityUrn": "urn:li:fs_languageView:ACoAAACh6xgB8s7a1lMm4grFoZBVsaZTKMHCZDs", "profileId": "ACoAAACh6xgB8s7a1lMm4grFoZBVsaZTKMHCZDs", "elements": [], "paging": "urn:li:fs_languageView:ACoAAACh6xgB8s7a1lMm4grFoZBVsaZTKMHCZDs,paging", "$type": "com.linkedin.voyager.identity.profile.LanguageView"}, {"$deletedFields": [], "entityUrn": "urn:li:fs_organizationView:ACoAAACh6xgB8s7a1lMm4grFoZBVsaZTKMHCZDs", "profileId": "ACoAAACh6xgB8s7a1lMm4grFoZBVsaZTKMHCZDs", "elements": [], "paging": "urn:li:fs_organizationView:ACoAAACh6xgB8s7a1lMm4grFoZBVsaZTKMHCZDs,paging", "$type": "com.linkedin.voyager.identity.profile.OrganizationView"}, {"$deletedFields": [], "entityUrn": "urn:li:fs_patentView:ACoAAACh6xgB8s7a1lMm4grFoZBVsaZTKMHCZDs", "profileId": "ACoAAACh6xgB8s7a1lMm4grFoZBVsaZTKMHCZDs", "elements": [], "paging": "urn:li:fs_patentView:ACoAAACh6xgB8s7a1lMm4grFoZBVsaZTKMHCZDs,paging", "$type": "com.linkedin.voyager.identity.profile.PatentView"}, {"$deletedFields": ["courses", "projects", "recommendations", "honors", "entityLocale", "organizations", "region"], "locationName": "Dallas/Fort Worth Area", "entityUrn": "urn:li:fs_position:(ACoAAACh6xgB8s7a1lMm4grFoZBVsaZTKMHCZDs,14500686)", "companyName": "Accenture", "timePeriod": "urn:li:fs_position:(ACoAAACh6xgB8s7a1lMm4grFoZBVsaZTKMHCZDs,14500686),timePeriod", "description": "Ahmed launched client's first digital product which generated strong revenue from day one and maintained a 92% retention rate.  Ahmed played a key role in the following areas;\n\nFacilitating vision definition with CEO\nDefining effective business and pricing models\nDefining MVO for public beta which was launched national conference\nBuilding a small, effective cross-functional team\nNavigating team through technology selection decisions\nManaging content creation and broadcasting schedule \nMasterminding the product launch demo and launch-day special offering", "company": "urn:li:fs_position:(ACoAAACh6xgB8s7a1lMm4grFoZBVsaZTKMHCZDs,14500686),company", "title": "UX Consultant, Products & Portals Practice", "companyUrn": "urn:li:fs_miniCompany:1033", "$type": "com.linkedin.voyager.identity.profile.Position"}, {"$deletedFields": ["courses", "locationName", "projects", "companyUrn", "recommendations", "honors", "entityLocale", "organizations", "company", "region"], "entityUrn": "urn:li:fs_position:(ACoAAACh6xgB8s7a1lMm4grFoZBVsaZTKMHCZDs,1139733168)", "companyName": "Sketch App", "timePeriod": "urn:li:fs_position:(ACoAAACh6xgB8s7a1lMm4grFoZBVsaZTKMHCZDs,1139733168),timePeriod", "description": "Sketch App is the leading digital product design tool for thousands of designers. Ahmed is the Co Organizer of the official meetup for the Dallas chapter.", "title": "Meetup Co Organizer, Dallas", "$type": "com.linkedin.voyager.identity.profile.Position"}, {"$deletedFields": ["courses", "projects", "recommendations", "honors", "entityLocale", "organizations", "region"], "locationName": "Dallas/Fort Worth Area", "entityUrn": "urn:li:fs_position:(ACoAAACh6xgB8s7a1lMm4grFoZBVsaZTKMHCZDs,643247363)", "companyName": "tekzenit, Inc.", "timePeriod": "urn:li:fs_position:(ACoAAACh6xgB8s7a1lMm4grFoZBVsaZTKMHCZDs,643247363),timePeriod", "description": "AT&T reinvisioned its enterprise and small business multi-channel offerings which required a redesign and development from the ground up\n\nRESULTS\nAhmed lead AT&T in transforming B2B billing experience which helped drive executive initiative to digitizing core business by 2020.\n\n- Elected to be part of the executive Program Vision Team which shaped the product roadmap\n- Presented feature prioritization based on customer needs, development effort and business value\n- Introduced design activities such as design studio and design reviews to the process\n- Mentor junior designers in prototyping, interaction design and information architecture", "company": "urn:li:fs_position:(ACoAAACh6xgB8s7a1lMm4grFoZBVsaZTKMHCZDs,643247363),company", "title": "UX Lead, AT&T Business", "companyUrn": "urn:li:fs_miniCompany:1459397", "$type": "com.linkedin.voyager.identity.profile.Position"}, {"$deletedFields": ["courses", "projects", "recommendations", "honors", "entityLocale", "organizations", "region"], "locationName": "Dallas/Fort Worth Area", "entityUrn": "urn:li:fs_position:(ACoAAACh6xgB8s7a1lMm4grFoZBVsaZTKMHCZDs,643248594)", "companyName": "Credera", "timePeriod": "urn:li:fs_position:(ACoAAACh6xgB8s7a1lMm4grFoZBVsaZTKMHCZDs,643248594),timePeriod", "description": "RESULTS\nFor a national resourcing client, Ahmed served as the principal mobile strategist and design consultant.\n\n- Average time to submit went from 38 minutes to 4 minutes (9.5 times faster) \n- Average time to complete onboarding from 24 hrs to less than 1 hour (24 times faster) \n- Doubled the # of applicants completing onboarding \n- Moving job application processing to be 60% on mobile\n- Roadmap a mobile web strategy that led to faster results client\u00e2\u0080\u0099s original plan\n\nProduct Leadership\n- Guided COO in making the mobile web vs native app decision\n- Simplified feature and capabilities list to what was most critically needed\n- Prepared COO for internal demo to get buy and feedback\n\nUser Experience\n- Briefed on the value of design and UX processes\n- Identified and educated team about problems of using print design approach\n- Served as the sole designer for creating the companies first mobile experience\n- Made design flexible to work with companies 13 different brands", "company": "urn:li:fs_position:(ACoAAACh6xgB8s7a1lMm4grFoZBVsaZTKMHCZDs,643248594),company", "title": "Sr. Consultant, Experience Strategy & Design", "companyUrn": "urn:li:fs_miniCompany:21837", "$type": "com.linkedin.voyager.identity.profile.Position"}, {"$deletedFields": ["courses", "projects", "description", "recommendations", "honors", "entityLocale", "organizations", "region"], "locationName": "Dallas/Fort Worth Area", "entityUrn": "urn:li:fs_position:(ACoAAACh6xgB8s7a1lMm4grFoZBVsaZTKMHCZDs,643251424)", "companyName": "WebEx", "timePeriod": "urn:li:fs_position:(ACoAAACh6xgB8s7a1lMm4grFoZBVsaZTKMHCZDs,643251424),timePeriod", "company": "urn:li:fs_position:(ACoAAACh6xgB8s7a1lMm4grFoZBVsaZTKMHCZDs,643251424),company", "title": "UX Lead, Business User Experience", "companyUrn": "urn:li:fs_miniCompany:3805", "$type": "com.linkedin.voyager.identity.profile.Position"}, {"employeeCountRange": "urn:li:fs_position:(ACoAAACh6xgB8s7a1lMm4grFoZBVsaZTKMHCZDs,643247363),company,employeeCountRange", "$deletedFields": [], "miniCompany": "urn:li:fs_miniCompany:1459397", "industries": ["Information Technology and Services"], "$type": "com.linkedin.voyager.identity.profile.PositionCompany", "$id": "urn:li:fs_position:(ACoAAACh6xgB8s7a1lMm4grFoZBVsaZTKMHCZDs,643247363),company"}, {"employeeCountRange": "urn:li:fs_position:(ACoAAACh6xgB8s7a1lMm4grFoZBVsaZTKMHCZDs,643251424),company,employeeCountRange", "$deletedFields": [], "miniCompany": "urn:li:fs_miniCompany:3805", "industries": ["Telecommunications"], "$type": "com.linkedin.voyager.identity.profile.PositionCompany", "$id": "urn:li:fs_position:(ACoAAACh6xgB8s7a1lMm4grFoZBVsaZTKMHCZDs,643251424),company"}, {"employeeCountRange": "urn:li:fs_position:(ACoAAACh6xgB8s7a1lMm4grFoZBVsaZTKMHCZDs,14500686),company,employeeCountRange", "$deletedFields": [], "miniCompany": "urn:li:fs_miniCompany:1033", "industries": ["Information Technology and Services"], "$type": "com.linkedin.voyager.identity.profile.PositionCompany", "$id": "urn:li:fs_position:(ACoAAACh6xgB8s7a1lMm4grFoZBVsaZTKMHCZDs,14500686),company"}, {"employeeCountRange": "urn:li:fs_position:(ACoAAACh6xgB8s7a1lMm4grFoZBVsaZTKMHCZDs,643248594),company,employeeCountRange", "$deletedFields": [], "miniCompany": "urn:li:fs_miniCompany:21837", "industries": ["Information Technology and Services"], "$type": "com.linkedin.voyager.identity.profile.PositionCompany", "$id": "urn:li:fs_position:(ACoAAACh6xgB8s7a1lMm4grFoZBVsaZTKMHCZDs,643248594),company"}, {"$deletedFields": [], "entityUrn": "urn:li:fs_positionView:ACoAAACh6xgB8s7a1lMm4grFoZBVsaZTKMHCZDs", "profileId": "ACoAAACh6xgB8s7a1lMm4grFoZBVsaZTKMHCZDs", "elements": ["urn:li:fs_position:(ACoAAACh6xgB8s7a1lMm4grFoZBVsaZTKMHCZDs,1139733168)", "urn:li:fs_position:(ACoAAACh6xgB8s7a1lMm4grFoZBVsaZTKMHCZDs,643251424)", "urn:li:fs_position:(ACoAAACh6xgB8s7a1lMm4grFoZBVsaZTKMHCZDs,643247363)", "urn:li:fs_position:(ACoAAACh6xgB8s7a1lMm4grFoZBVsaZTKMHCZDs,643248594)", "urn:li:fs_position:(ACoAAACh6xgB8s7a1lMm4grFoZBVsaZTKMHCZDs,14500686)"], "paging": "urn:li:fs_positionView:ACoAAACh6xgB8s7a1lMm4grFoZBVsaZTKMHCZDs,paging", "$type": "com.linkedin.voyager.identity.profile.PositionView"}, {"summary": "Ahmed leads teams to create products users love.\n\nIn the past 14 years, he has successfully taken new consumer and business products from ideas to inception to positive inflection points.  Though he has learned invaluable lessons from his failures, many of them created measurable increases in engagement and revenue for startups and Fortune 500 companies.", "industryName": "Design", "lastName": "Arshad", "supportedLocales": ["urn:li:fs_profile:ACoAAACh6xgB8s7a1lMm4grFoZBVsaZTKMHCZDs,supportedLocales,1204a34c-a6cf-4a96-a302-ef4fa907b34c-0"], "locationName": "Dallas/Fort Worth Area", "versionTag": "2107824812", "industryUrn": "urn:li:fs_industry:99", "$type": "com.linkedin.voyager.identity.profile.Profile", "defaultLocale": "urn:li:fs_profileView:ACoAAACh6xgB8s7a1lMm4grFoZBVsaZTKMHCZDs,primaryLocale", "firstName": "Ahmed", "$deletedFields": ["backgroundImage", "maidenName", "phoneticLastName", "contactInstructions", "entityLocale", "state", "phoneticFirstName", "address", "pictureInfo", "profilePictureOriginalImage", "birthDate", "profilePicture", "interests", "backgroundPicture", "backgroundPictureOriginalImage"], "showEducationOnProfileTopCard": true, "entityUrn": "urn:li:fs_profile:ACoAAACh6xgB8s7a1lMm4grFoZBVsaZTKMHCZDs", "location": "urn:li:fs_profile:ACoAAACh6xgB8s7a1lMm4grFoZBVsaZTKMHCZDs,location", "miniProfile": "urn:li:fs_miniProfile:ACoAAACh6xgB8s7a1lMm4grFoZBVsaZTKMHCZDs", "headline": "User Experience Design Leader"}, {"$deletedFields": [], "basicLocation": "urn:li:fs_profile:ACoAAACh6xgB8s7a1lMm4grFoZBVsaZTKMHCZDs,location,basicLocation", "preferredGeoPlace": "urn:li:fs_region:(us,31)", "$type": "com.linkedin.voyager.identity.profile.ProfileLocation", "$id": "urn:li:fs_profile:ACoAAACh6xgB8s7a1lMm4grFoZBVsaZTKMHCZDs,location"}, {"$deletedFields": [], "entityUrn": "urn:li:fs_projectView:ACoAAACh6xgB8s7a1lMm4grFoZBVsaZTKMHCZDs", "profileId": "ACoAAACh6xgB8s7a1lMm4grFoZBVsaZTKMHCZDs", "elements": [], "paging": "urn:li:fs_projectView:ACoAAACh6xgB8s7a1lMm4grFoZBVsaZTKMHCZDs,paging", "$type": "com.linkedin.voyager.identity.profile.ProjectView"}, {"date": "urn:li:fs_publication:(ACoAAACh6xgB8s7a1lMm4grFoZBVsaZTKMHCZDs,300725221),date", "$deletedFields": [], "entityUrn": "urn:li:fs_publication:(ACoAAACh6xgB8s7a1lMm4grFoZBVsaZTKMHCZDs,300725221)", "name": "Product Adoption: The Overlooked Phase of User Experience", "publisher": "Cisco Systems", "description": "\"Even though there a strong race to ship products with a great user experience, what happens after the customer buys and deploys it is very different.\"", "url": "https://blogs.cisco.com/collaboration/product-adoption-overlooked-phase-of-ux#", "authors": ["urn:li:fs_contributor:(ACoAAACh6xgB8s7a1lMm4grFoZBVsaZTKMHCZDs,300725221,140185630)"], "$type": "com.linkedin.voyager.identity.profile.Publication"}, {"date": "urn:li:fs_publication:(ACoAAACh6xgB8s7a1lMm4grFoZBVsaZTKMHCZDs,224),date", "$deletedFields": ["publisher"], "entityUrn": "urn:li:fs_publication:(ACoAAACh6xgB8s7a1lMm4grFoZBVsaZTKMHCZDs,224)", "name": "4 Critical Strategies for Recreating Enterprise Products", "description": "You can sense the positive energy in the hallways when a department\u00e2\u0080\u0099s budget is approved to reimagine an existing enterprise product. It is especially exciting if the decades old product has been a point of frustration for the company\u00e2\u0080\u0099s goals & their users\u00e2\u0080\u0099 experience.", "url": "https://medium.com/@ahmedbarshad/4-critical-strategies-for-recreating-enterprise-product-3957266cef8d?source=tw-661f9c9f92b5-1416103383624", "authors": ["urn:li:fs_contributor:(ACoAAACh6xgB8s7a1lMm4grFoZBVsaZTKMHCZDs,224,225)"], "$type": "com.linkedin.voyager.identity.profile.Publication"}, {"$deletedFields": [], "entityUrn": "urn:li:fs_publicationView:ACoAAACh6xgB8s7a1lMm4grFoZBVsaZTKMHCZDs", "profileId": "ACoAAACh6xgB8s7a1lMm4grFoZBVsaZTKMHCZDs", "elements": ["urn:li:fs_publication:(ACoAAACh6xgB8s7a1lMm4grFoZBVsaZTKMHCZDs,300725221)", "urn:li:fs_publication:(ACoAAACh6xgB8s7a1lMm4grFoZBVsaZTKMHCZDs,224)"], "paging": "urn:li:fs_publicationView:ACoAAACh6xgB8s7a1lMm4grFoZBVsaZTKMHCZDs,paging", "$type": "com.linkedin.voyager.identity.profile.PublicationView"}, {"$deletedFields": ["standardizedSkillUrn", "standardizedSkill"], "entityUrn": "urn:li:fs_skill:(ACoAAACh6xgB8s7a1lMm4grFoZBVsaZTKMHCZDs,4)", "name": "Information Architecture", "$type": "com.linkedin.voyager.identity.profile.Skill"}, {"$deletedFields": ["standardizedSkillUrn", "standardizedSkill"], "entityUrn": "urn:li:fs_skill:(ACoAAACh6xgB8s7a1lMm4grFoZBVsaZTKMHCZDs,3)", "name": "Interaction Design", "$type": "com.linkedin.voyager.identity.profile.Skill"}, {"$deletedFields": ["standardizedSkillUrn", "standardizedSkill"], "entityUrn": "urn:li:fs_skill:(ACoAAACh6xgB8s7a1lMm4grFoZBVsaZTKMHCZDs,2)", "name": "User-centered Design", "$type": "com.linkedin.voyager.identity.profile.Skill"}, {"$deletedFields": ["standardizedSkillUrn", "standardizedSkill"], "entityUrn": "urn:li:fs_skill:(ACoAAACh6xgB8s7a1lMm4grFoZBVsaZTKMHCZDs,1)", "name": "User Experience", "$type": "com.linkedin.voyager.identity.profile.Skill"}, {"$deletedFields": [], "entityUrn": "urn:li:fs_skillView:ACoAAACh6xgB8s7a1lMm4grFoZBVsaZTKMHCZDs", "profileId": "ACoAAACh6xgB8s7a1lMm4grFoZBVsaZTKMHCZDs", "elements": ["urn:li:fs_skill:(ACoAAACh6xgB8s7a1lMm4grFoZBVsaZTKMHCZDs,1)", "urn:li:fs_skill:(ACoAAACh6xgB8s7a1lMm4grFoZBVsaZTKMHCZDs,2)", "urn:li:fs_skill:(ACoAAACh6xgB8s7a1lMm4grFoZBVsaZTKMHCZDs,3)", "urn:li:fs_skill:(ACoAAACh6xgB8s7a1lMm4grFoZBVsaZTKMHCZDs,4)"], "paging": "urn:li:fs_skillView:ACoAAACh6xgB8s7a1lMm4grFoZBVsaZTKMHCZDs,paging", "$type": "com.linkedin.voyager.identity.profile.SkillView"}, {"$deletedFields": [], "entityUrn": "urn:li:fs_testScoreView:ACoAAACh6xgB8s7a1lMm4grFoZBVsaZTKMHCZDs", "profileId": "ACoAAACh6xgB8s7a1lMm4grFoZBVsaZTKMHCZDs", "elements": [], "paging": "urn:li:fs_testScoreView:ACoAAACh6xgB8s7a1lMm4grFoZBVsaZTKMHCZDs,paging", "$type": "com.linkedin.voyager.identity.profile.TestScoreView"}, {"$deletedFields": [], "entityUrn": "urn:li:fs_volunteerCauseView:ACoAAACh6xgB8s7a1lMm4grFoZBVsaZTKMHCZDs", "profileId": "ACoAAACh6xgB8s7a1lMm4grFoZBVsaZTKMHCZDs", "elements": [], "paging": "urn:li:fs_volunteerCauseView:ACoAAACh6xgB8s7a1lMm4grFoZBVsaZTKMHCZDs,paging", "$type": "com.linkedin.voyager.identity.profile.VolunteerCauseView"}, {"$deletedFields": [], "entityUrn": "urn:li:fs_volunteerExperienceView:ACoAAACh6xgB8s7a1lMm4grFoZBVsaZTKMHCZDs", "profileId": "ACoAAACh6xgB8s7a1lMm4grFoZBVsaZTKMHCZDs", "elements": [], "paging": "urn:li:fs_volunteerExperienceView:ACoAAACh6xgB8s7a1lMm4grFoZBVsaZTKMHCZDs,paging", "$type": "com.linkedin.voyager.identity.profile.VolunteerExperienceView"}, {"firstName": "Ahmed", "lastName": "Arshad", "$deletedFields": [], "occupation": "User Experience Design Leader", "objectUrn": "urn:li:member:10611480", "entityUrn": "urn:li:fs_miniProfile:ACoAAACh6xgB8s7a1lMm4grFoZBVsaZTKMHCZDs", "backgroundImage": {"com.linkedin.common.VectorImage": "urn:li:fs_miniProfile:ACoAAACh6xgB8s7a1lMm4grFoZBVsaZTKMHCZDs,backgroundImage,com.linkedin.common.VectorImage"}, "publicIdentifier": "ahmedbarshad", "picture": {"com.linkedin.common.VectorImage": "urn:li:fs_miniProfile:ACoAAACh6xgB8s7a1lMm4grFoZBVsaZTKMHCZDs,picture,com.linkedin.common.VectorImage"}, "trackingId": "CLA2bTGRQJOXJzyrrHo+wQ==", "$type": "com.linkedin.voyager.identity.shared.MiniProfile"}]}, "28": {"request": "/voyager/api/identity/profiles/ahmedbarshad/profileView", "status": 200, "body": "bpr-guid-339921"}, "29": {"statuses": {}, "results": {"publicProfile.removeModulesExperiments": {"treatment": "control", "testKey": "publicProfile.removeModulesExperiments"}}, "errors": {}}, "30": {"request": "/voyager/api/lixTreatments?ids=List(publicProfile.removeModulesExperiments)&target=urn%3Ali%3Aurl%3A0", "status": 200, "body": "bpr-guid-339924"}}