{"1": {"data": {"$deletedFields": ["launchAlert"], "mediaConfig": "crc4KtMwSB9CyP/2sFIqSw==,root,mediaConfig", "$type": "com.linkedin.voyager.common.Configuration", "$id": "crc4KtMwSB9CyP/2sFIqSw==,root"}, "included": [{"mprConfig": "crc4KtMwSB9CyP/2sFIqSw==,root,mediaConfig,mprConfig", "$deletedFields": [], "$type": "com.linkedin.voyager.common.MediaConfig", "$id": "crc4KtMwSB9CyP/2sFIqSw==,root,mediaConfig"}, {"$deletedFields": [], "sizes": ["crc4KtMwSB9CyP/2sFIqSw==,root,mediaConfig,mprConfig,sizes,075a9e52-e550-4250-982d-3ff82d85c0c3-0", "crc4KtMwSB9CyP/2sFIqSw==,root,mediaConfig,mprConfig,sizes,075a9e52-e550-4250-982d-3ff82d85c0c3-1", "crc4KtMwSB9CyP/2sFIqSw==,root,mediaConfig,mprConfig,sizes,075a9e52-e550-4250-982d-3ff82d85c0c3-2", "crc4KtMwSB9CyP/2sFIqSw==,root,mediaConfig,mprConfig,sizes,075a9e52-e550-4250-982d-3ff82d85c0c3-3", "crc4KtMwSB9CyP/2sFIqSw==,root,mediaConfig,mprConfig,sizes,075a9e52-e550-4250-982d-3ff82d85c0c3-4", "crc4KtMwSB9CyP/2sFIqSw==,root,mediaConfig,mprConfig,sizes,075a9e52-e550-4250-982d-3ff82d85c0c3-5", "crc4KtMwSB9CyP/2sFIqSw==,root,mediaConfig,mprConfig,sizes,075a9e52-e550-4250-982d-3ff82d85c0c3-6", "crc4KtMwSB9CyP/2sFIqSw==,root,mediaConfig,mprConfig,sizes,075a9e52-e550-4250-982d-3ff82d85c0c3-7", "crc4KtMwSB9CyP/2sFIqSw==,root,mediaConfig,mprConfig,sizes,075a9e52-e550-4250-982d-3ff82d85c0c3-8", "crc4KtMwSB9CyP/2sFIqSw==,root,mediaConfig,mprConfig,sizes,075a9e52-e550-4250-982d-3ff82d85c0c3-9", "crc4KtMwSB9CyP/2sFIqSw==,root,mediaConfig,mprConfig,sizes,075a9e52-e550-4250-982d-3ff82d85c0c3-10", "crc4KtMwSB9CyP/2sFIqSw==,root,mediaConfig,mprConfig,sizes,075a9e52-e550-4250-982d-3ff82d85c0c3-11", "crc4KtMwSB9CyP/2sFIqSw==,root,mediaConfig,mprConfig,sizes,075a9e52-e550-4250-982d-3ff82d85c0c3-12", "crc4KtMwSB9CyP/2sFIqSw==,root,mediaConfig,mprConfig,sizes,075a9e52-e550-4250-982d-3ff82d85c0c3-13", "crc4KtMwSB9CyP/2sFIqSw==,root,mediaConfig,mprConfig,sizes,075a9e52-e550-4250-982d-3ff82d85c0c3-14", "crc4KtMwSB9CyP/2sFIqSw==,root,mediaConfig,mprConfig,sizes,075a9e52-e550-4250-982d-3ff82d85c0c3-15", "crc4KtMwSB9CyP/2sFIqSw==,root,mediaConfig,mprConfig,sizes,075a9e52-e550-4250-982d-3ff82d85c0c3-16", "crc4KtMwSB9CyP/2sFIqSw==,root,mediaConfig,mprConfig,sizes,075a9e52-e550-4250-982d-3ff82d85c0c3-17", "crc4KtMwSB9CyP/2sFIqSw==,root,mediaConfig,mprConfig,sizes,075a9e52-e550-4250-982d-3ff82d85c0c3-18", "crc4KtMwSB9CyP/2sFIqSw==,root,mediaConfig,mprConfig,sizes,075a9e52-e550-4250-982d-3ff82d85c0c3-19", "crc4KtMwSB9CyP/2sFIqSw==,root,mediaConfig,mprConfig,sizes,075a9e52-e550-4250-982d-3ff82d85c0c3-20", "crc4KtMwSB9CyP/2sFIqSw==,root,mediaConfig,mprConfig,sizes,075a9e52-e550-4250-982d-3ff82d85c0c3-21", "crc4KtMwSB9CyP/2sFIqSw==,root,mediaConfig,mprConfig,sizes,075a9e52-e550-4250-982d-3ff82d85c0c3-22", "crc4KtMwSB9CyP/2sFIqSw==,root,mediaConfig,mprConfig,sizes,075a9e52-e550-4250-982d-3ff82d85c0c3-23", "crc4KtMwSB9CyP/2sFIqSw==,root,mediaConfig,mprConfig,sizes,075a9e52-e550-4250-982d-3ff82d85c0c3-24"], "filters": "crc4KtMwSB9CyP/2sFIqSw==,root,mediaConfig,mprConfig,filters", "$type": "com.linkedin.voyager.common.MediaProcessorConfig", "$id": "crc4KtMwSB9CyP/2sFIqSw==,root,mediaConfig,mprConfig"}, {"cover": "https://media.licdn.com/mpr/mpr/shrinknp_{width}_{height}{+id}", "$deletedFields": [], "contain": "https://media.licdn.com/mpr/mpr/shrinknp_{width}_{height}{+id}", "original": "https://media.licdn.com/media{+id}", "fill": "https://media.licdn.com/mpr/mpr/shrink_{width}_{height}{+id}", "$type": "com.linkedin.voyager.common.MediaProcessorFilters", "$id": "crc4KtMwSB9CyP/2sFIqSw==,root,mediaConfig,mprConfig,filters"}, {"$deletedFields": [], "width": 254, "height": 92, "$type": "com.linkedin.voyager.common.MediaProcessorSize", "$id": "crc4KtMwSB9CyP/2sFIqSw==,root,mediaConfig,mprConfig,sizes,075a9e52-e550-4250-982d-3ff82d85c0c3-19"}, {"$deletedFields": [], "width": 254, "height": 60, "$type": "com.linkedin.voyager.common.MediaProcessorSize", "$id": "crc4KtMwSB9CyP/2sFIqSw==,root,mediaConfig,mprConfig,sizes,075a9e52-e550-4250-982d-3ff82d85c0c3-18"}, {"$deletedFields": [], "width": 200, "height": 100, "$type": "com.linkedin.voyager.common.MediaProcessorSize", "$id": "crc4KtMwSB9CyP/2sFIqSw==,root,mediaConfig,mprConfig,sizes,075a9e52-e550-4250-982d-3ff82d85c0c3-15"}, {"$deletedFields": [], "width": 191, "height": 69, "$type": "com.linkedin.voyager.common.MediaProcessorSize", "$id": "crc4KtMwSB9CyP/2sFIqSw==,root,mediaConfig,mprConfig,sizes,075a9e52-e550-4250-982d-3ff82d85c0c3-14"}, {"$deletedFields": [], "width": 200, "height": 200, "$type": "com.linkedin.voyager.common.MediaProcessorSize", "$id": "crc4KtMwSB9CyP/2sFIqSw==,root,mediaConfig,mprConfig,sizes,075a9e52-e550-4250-982d-3ff82d85c0c3-17"}, {"$deletedFields": [], "width": 200, "height": 120, "$type": "com.linkedin.voyager.common.MediaProcessorSize", "$id": "crc4KtMwSB9CyP/2sFIqSw==,root,mediaConfig,mprConfig,sizes,075a9e52-e550-4250-982d-3ff82d85c0c3-16"}, {"$deletedFields": [], "width": 150, "height": 75, "$type": "com.linkedin.voyager.common.MediaProcessorSize", "$id": "crc4KtMwSB9CyP/2sFIqSw==,root,mediaConfig,mprConfig,sizes,075a9e52-e550-4250-982d-3ff82d85c0c3-11"}, {"$deletedFields": [], "width": 127, "height": 46, "$type": "com.linkedin.voyager.common.MediaProcessorSize", "$id": "crc4KtMwSB9CyP/2sFIqSw==,root,mediaConfig,mprConfig,sizes,075a9e52-e550-4250-982d-3ff82d85c0c3-10"}, {"$deletedFields": [], "width": 191, "height": 45, "$type": "com.linkedin.voyager.common.MediaProcessorSize", "$id": "crc4KtMwSB9CyP/2sFIqSw==,root,mediaConfig,mprConfig,sizes,075a9e52-e550-4250-982d-3ff82d85c0c3-13"}, {"$deletedFields": [], "width": 150, "height": 90, "$type": "com.linkedin.voyager.common.MediaProcessorSize", "$id": "crc4KtMwSB9CyP/2sFIqSw==,root,mediaConfig,mprConfig,sizes,075a9e52-e550-4250-982d-3ff82d85c0c3-12"}, {"$deletedFields": [], "width": 90, "height": 45, "$type": "com.linkedin.voyager.common.MediaProcessorSize", "$id": "crc4KtMwSB9CyP/2sFIqSw==,root,mediaConfig,mprConfig,sizes,075a9e52-e550-4250-982d-3ff82d85c0c3-2"}, {"$deletedFields": [], "width": 60, "height": 36, "$type": "com.linkedin.voyager.common.MediaProcessorSize", "$id": "crc4KtMwSB9CyP/2sFIqSw==,root,mediaConfig,mprConfig,sizes,075a9e52-e550-4250-982d-3ff82d85c0c3-1"}, {"$deletedFields": [], "width": 100, "height": 50, "$type": "com.linkedin.voyager.common.MediaProcessorSize", "$id": "crc4KtMwSB9CyP/2sFIqSw==,root,mediaConfig,mprConfig,sizes,075a9e52-e550-4250-982d-3ff82d85c0c3-4"}, {"$deletedFields": [], "width": 90, "height": 54, "$type": "com.linkedin.voyager.common.MediaProcessorSize", "$id": "crc4KtMwSB9CyP/2sFIqSw==,root,mediaConfig,mprConfig,sizes,075a9e52-e550-4250-982d-3ff82d85c0c3-3"}, {"$deletedFields": [], "width": 60, "height": 30, "$type": "com.linkedin.voyager.common.MediaProcessorSize", "$id": "crc4KtMwSB9CyP/2sFIqSw==,root,mediaConfig,mprConfig,sizes,075a9e52-e550-4250-982d-3ff82d85c0c3-0"}, {"$deletedFields": [], "width": 127, "height": 30, "$type": "com.linkedin.voyager.common.MediaProcessorSize", "$id": "crc4KtMwSB9CyP/2sFIqSw==,root,mediaConfig,mprConfig,sizes,075a9e52-e550-4250-982d-3ff82d85c0c3-9"}, {"$deletedFields": [], "width": 100, "height": 100, "$type": "com.linkedin.voyager.common.MediaProcessorSize", "$id": "crc4KtMwSB9CyP/2sFIqSw==,root,mediaConfig,mprConfig,sizes,075a9e52-e550-4250-982d-3ff82d85c0c3-6"}, {"$deletedFields": [], "width": 100, "height": 60, "$type": "com.linkedin.voyager.common.MediaProcessorSize", "$id": "crc4KtMwSB9CyP/2sFIqSw==,root,mediaConfig,mprConfig,sizes,075a9e52-e550-4250-982d-3ff82d85c0c3-5"}, {"$deletedFields": [], "width": 120, "height": 72, "$type": "com.linkedin.voyager.common.MediaProcessorSize", "$id": "crc4KtMwSB9CyP/2sFIqSw==,root,mediaConfig,mprConfig,sizes,075a9e52-e550-4250-982d-3ff82d85c0c3-8"}, {"$deletedFields": [], "width": 120, "height": 60, "$type": "com.linkedin.voyager.common.MediaProcessorSize", "$id": "crc4KtMwSB9CyP/2sFIqSw==,root,mediaConfig,mprConfig,sizes,075a9e52-e550-4250-982d-3ff82d85c0c3-7"}, {"$deletedFields": [], "width": 506, "height": 180, "$type": "com.linkedin.voyager.common.MediaProcessorSize", "$id": "crc4KtMwSB9CyP/2sFIqSw==,root,mediaConfig,mprConfig,sizes,075a9e52-e550-4250-982d-3ff82d85c0c3-22"}, {"$deletedFields": [], "width": 400, "height": 400, "$type": "com.linkedin.voyager.common.MediaProcessorSize", "$id": "crc4KtMwSB9CyP/2sFIqSw==,root,mediaConfig,mprConfig,sizes,075a9e52-e550-4250-982d-3ff82d85c0c3-21"}, {"$deletedFields": [], "width": 750, "height": 750, "$type": "com.linkedin.voyager.common.MediaProcessorSize", "$id": "crc4KtMwSB9CyP/2sFIqSw==,root,mediaConfig,mprConfig,sizes,075a9e52-e550-4250-982d-3ff82d85c0c3-24"}, {"$deletedFields": [], "width": 674, "height": 240, "$type": "com.linkedin.voyager.common.MediaProcessorSize", "$id": "crc4KtMwSB9CyP/2sFIqSw==,root,mediaConfig,mprConfig,sizes,075a9e52-e550-4250-982d-3ff82d85c0c3-23"}, {"$deletedFields": [], "width": 337, "height": 120, "$type": "com.linkedin.voyager.common.MediaProcessorSize", "$id": "crc4KtMwSB9CyP/2sFIqSw==,root,mediaConfig,mprConfig,sizes,075a9e52-e550-4250-982d-3ff82d85c0c3-20"}]}, "2": {"request": "/voyager/api/configuration", "status": 200, "body": "bpr-guid-316178"}, "3": {"data": {"canBrowseProfiles": false, "$deletedFields": [], "reactivationFeaturesEligible": true, "canViewJobAnalytics": true, "canViewWVMP": true, "canViewCompanyInsights": false, "$type": "com.linkedin.voyager.premium.FeatureAccess", "$id": "rp3HQ6ObDeupY3gQ84tYJw==,root"}, "included": []}, "4": {"request": "/voyager/api/premium/featureAccess?name=reactivationFeaturesEligible", "status": 200, "body": "bpr-guid-316179"}, "5": {"data": {"paidProducts": ["LEARNING"], "companies": [], "$deletedFields": ["postJobsEnabled"], "memberGroup": "PREMIUM", "showStaticLearning": false, "$type": "com.linkedin.voyager.common.Nav", "$id": "M8x5UY0Zt6eGdBCiy+iKhA==,root"}, "included": []}, "6": {"request": "/voyager/api/nav", "status": 200, "body": "bpr-guid-316180"}, "7": {"data": {"messagingTypingIndicators": "ALL_DISABLED", "allowOpenProfile": true, "profilePictureVisibilitySetting": "PUBLIC", "$deletedFields": [], "entityUrn": "urn:li:fs_privacySettings:ACoAABxrN-8Bf2FB9s1yzswU9yjVHdbJzRVGgvU", "showPublicProfile": true, "showPremiumSubscriberBadge": true, "publicProfilePictureVisibilitySetting": "PUBLIC", "formerNameVisibilitySetting": "CONNECTIONS", "messagingSeenReceipts": "ALL_DISABLED", "allowProfileEditBroadcasts": false, "$type": "com.linkedin.voyager.identity.profile.PrivacySettings"}, "included": []}, "8": {"request": "/voyager/api/identity/profiles/josue-hurtado-a88b831/privacySettings", "status": 200, "body": "bpr-guid-316181"}, "9": {"data": {"elements": [], "paging": {"total": 0, "count": 10, "start": 0, "links": []}}, "included": []}, "10": {"request": "/voyager/api/takeovers", "status": 200, "body": "bpr-guid-316182"}, "11": {"data": {"$deletedFields": [], "publicContactInfo": "qTJ8dtboEoV+oq/pm1xyeA==,root,publicContactInfo", "plainId": 476788719, "miniProfile": "urn:li:fs_miniProfile:ACoAABxrN-8Bf2FB9s1yzswU9yjVHdbJzRVGgvU", "premiumSubscriber": true, "$type": "com.linkedin.voyager.common.Me", "$id": "qTJ8dtboEoV+oq/pm1xyeA==,root"}, "included": [{"$deletedFields": [], "width": 400, "fileIdentifyingUrlPathSegment": "400_400/0?e=1529391600&v=beta&t=wNM_XQh-KyyPMHzNfqwsEoh_Zbtf30YW1dkoaQXw_Xk", "height": 400, "$type": "com.linkedin.common.VectorArtifact", "$id": "urn:li:fs_miniProfile:ACoAABxrN-8Bf2FB9s1yzswU9yjVHdbJzRVGgvU,picture,com.linkedin.common.VectorImage,artifacts,be8c5f58-8f37-4e22-aae4-ac3a1f27e9bc-2"}, {"$deletedFields": [], "width": 200, "fileIdentifyingUrlPathSegment": "200_200/0?e=1529391600&v=beta&t=7XWx5gIqpSfvXbmxC9ntdG0kNlJjSJNmumX6todXo5g", "height": 200, "$type": "com.linkedin.common.VectorArtifact", "$id": "urn:li:fs_miniProfile:ACoAABxrN-8Bf2FB9s1yzswU9yjVHdbJzRVGgvU,picture,com.linkedin.common.VectorImage,artifacts,be8c5f58-8f37-4e22-aae4-ac3a1f27e9bc-1"}, {"$deletedFields": [], "width": 800, "fileIdentifyingUrlPathSegment": "800_800/0?e=1529391600&v=beta&t=tG2LoSlej2zVdkcw8J8w-58PJ0LRrv3XTSIBBHsvh9s", "height": 800, "$type": "com.linkedin.common.VectorArtifact", "$id": "urn:li:fs_miniProfile:ACoAABxrN-8Bf2FB9s1yzswU9yjVHdbJzRVGgvU,picture,com.linkedin.common.VectorImage,artifacts,be8c5f58-8f37-4e22-aae4-ac3a1f27e9bc-3"}, {"$deletedFields": [], "width": 100, "fileIdentifyingUrlPathSegment": "100_100/0?e=1529391600&v=beta&t=NPHcvvxW88F84Qz4qNgxepGxntu_c95qhHmvQWgU5nw", "height": 100, "$type": "com.linkedin.common.VectorArtifact", "$id": "urn:li:fs_miniProfile:ACoAABxrN-8Bf2FB9s1yzswU9yjVHdbJzRVGgvU,picture,com.linkedin.common.VectorImage,artifacts,be8c5f58-8f37-4e22-aae4-ac3a1f27e9bc-0"}, {"$deletedFields": ["attribution"], "artifacts": ["urn:li:fs_miniProfile:ACoAABxrN-8Bf2FB9s1yzswU9yjVHdbJzRVGgvU,picture,com.linkedin.common.VectorImage,artifacts,be8c5f58-8f37-4e22-aae4-ac3a1f27e9bc-0", "urn:li:fs_miniProfile:ACoAABxrN-8Bf2FB9s1yzswU9yjVHdbJzRVGgvU,picture,com.linkedin.common.VectorImage,artifacts,be8c5f58-8f37-4e22-aae4-ac3a1f27e9bc-1", "urn:li:fs_miniProfile:ACoAABxrN-8Bf2FB9s1yzswU9yjVHdbJzRVGgvU,picture,com.linkedin.common.VectorImage,artifacts,be8c5f58-8f37-4e22-aae4-ac3a1f27e9bc-2", "urn:li:fs_miniProfile:ACoAABxrN-8Bf2FB9s1yzswU9yjVHdbJzRVGgvU,picture,com.linkedin.common.VectorImage,artifacts,be8c5f58-8f37-4e22-aae4-ac3a1f27e9bc-3"], "rootUrl": "https://media.licdn.com/dms/image/C5103AQGEXWTXFMHyuw/profile-displayphoto-shrink_", "$type": "com.linkedin.common.VectorImage", "$id": "urn:li:fs_miniProfile:ACoAABxrN-8Bf2FB9s1yzswU9yjVHdbJzRVGgvU,picture,com.linkedin.common.VectorImage"}, {"firstName": "Yuan", "lastName": "Li", "$deletedFields": ["backgroundImage"], "occupation": "Graduate student at University of Michigan (MSI)", "objectUrn": "urn:li:member:476788719", "entityUrn": "urn:li:fs_miniProfile:ACoAABxrN-8Bf2FB9s1yzswU9yjVHdbJzRVGgvU", "publicIdentifier": "yuanlii", "picture": {"com.linkedin.common.VectorImage": "urn:li:fs_miniProfile:ACoAABxrN-8Bf2FB9s1yzswU9yjVHdbJzRVGgvU,picture,com.linkedin.common.VectorImage"}, "trackingId": "u9IDSKHIRA6c64pRiQvs8g==", "$type": "com.linkedin.voyager.identity.shared.MiniProfile"}, {"$deletedFields": [], "twitterHandles": [], "$type": "com.linkedin.voyager.identity.shared.PublicContactInfo", "$id": "qTJ8dtboEoV+oq/pm1xyeA==,root,publicContactInfo"}]}, "12": {"request": "/voyager/api/me", "status": 200, "body": "bpr-guid-316183"}, "13": {"data": {"$deletedFields": [], "followingInfo": "urn:li:fs_followingInfo:urn:li:member:ACoAAABZ9kgBnD4NsdiIMaVsiAQK3AwloLKM3Xk", "distance": "urn:li:fs_profileNetworkInfo:ACoAAABZ9kgBnD4NsdiIMaVsiAQK3AwloLKM3Xk,distance", "entityUrn": "urn:li:fs_profileNetworkInfo:ACoAAABZ9kgBnD4NsdiIMaVsiAQK3AwloLKM3Xk", "following": false, "followable": true, "followersCount": 240, "connectionsCount": 239, "$type": "com.linkedin.voyager.identity.profile.ProfileNetworkInfo"}, "included": [{"$deletedFields": ["followingCount"], "entityUrn": "urn:li:fs_followingInfo:urn:li:member:ACoAAABZ9kgBnD4NsdiIMaVsiAQK3AwloLKM3Xk", "following": false, "followerCount": 240, "$type": "com.linkedin.voyager.common.FollowingInfo"}, {"$deletedFields": [], "value": "DISTANCE_2", "$type": "com.linkedin.voyager.common.MemberDistance", "$id": "urn:li:fs_profileNetworkInfo:ACoAAABZ9kgBnD4NsdiIMaVsiAQK3AwloLKM3Xk,distance"}]}, "14": {"request": "/voyager/api/identity/profiles/josue-hurtado-a88b831/networkinfo", "status": 200, "body": "bpr-guid-316184"}, "15": {"data": {"elements": [], "paging": {"total": 0, "count": 10, "start": 0, "links": []}}, "included": []}, "16": {"request": "/voyager/api/identity/profiles/josue-hurtado-a88b831/treasuryMedia?q=sectionMedia&sectionId=summary", "status": 200, "body": "bpr-guid-316185"}, "17": {"data": {"elements": [], "paging": {"count": 10, "start": 0, "links": []}}, "included": []}, "18": {"request": "/voyager/api/identity/profiles/josue-hurtado-a88b831/treasuryMediaItems?q=backgroundMedia&section=EDUCATION", "status": 200, "body": "bpr-guid-316186"}, "19": {"data": {"elements": [], "paging": {"count": 10, "start": 0, "links": []}}, "included": []}, "20": {"request": "/voyager/api/identity/profiles/josue-hurtado-a88b831/treasuryMediaItems?q=backgroundMedia&section=POSITION", "status": 200, "body": "bpr-guid-316187"}, "21": {"data": {"$deletedFields": [], "versionTag": "1038066042", "$type": "com.linkedin.voyager.identity.profile.VersionTag", "$id": "0r6QfaWPmh9Ym9pFlhcGqg==,root"}, "included": []}, "22": {"request": "/voyager/api/identity/profiles/ACoAABxrN-8Bf2FB9s1yzswU9yjVHdbJzRVGgvU/versionTag", "status": 200, "body": "bpr-guid-316188"}, "23": {"data": {"$deletedFields": [], "premium": false, "influencer": false, "entityUrn": "urn:li:fs_memberBadges:ACoAAABZ9kgBnD4NsdiIMaVsiAQK3AwloLKM3Xk", "openLink": false, "jobSeeker": false, "$type": "com.linkedin.voyager.identity.profile.MemberBadges"}, "included": []}, "24": {"request": "/voyager/api/identity/profiles/josue-hurtado-a88b831/memberBadges", "status": 200, "body": "bpr-guid-316189"}, "25": {"data": {"patentView": "urn:li:fs_patentView:ACoAAABZ9kgBnD4NsdiIMaVsiAQK3AwloLKM3Xk", "educationView": "urn:li:fs_educationView:ACoAAABZ9kgBnD4NsdiIMaVsiAQK3AwloLKM3Xk", "organizationView": "urn:li:fs_organizationView:ACoAAABZ9kgBnD4NsdiIMaVsiAQK3AwloLKM3Xk", "projectView": "urn:li:fs_projectView:ACoAAABZ9kgBnD4NsdiIMaVsiAQK3AwloLKM3Xk", "positionView": "urn:li:fs_positionView:ACoAAABZ9kgBnD4NsdiIMaVsiAQK3AwloLKM3Xk", "profile": "urn:li:fs_profile:ACoAAABZ9kgBnD4NsdiIMaVsiAQK3AwloLKM3Xk", "languageView": "urn:li:fs_languageView:ACoAAABZ9kgBnD4NsdiIMaVsiAQK3AwloLKM3Xk", "certificationView": "urn:li:fs_certificationView:ACoAAABZ9kgBnD4NsdiIMaVsiAQK3AwloLKM3Xk", "$type": "com.linkedin.voyager.identity.profile.ProfileView", "$deletedFields": ["summaryTreasuryMediaCount", "summaryTreasuryMedias", "entityLocale"], "testScoreView": "urn:li:fs_testScoreView:ACoAAABZ9kgBnD4NsdiIMaVsiAQK3AwloLKM3Xk", "volunteerCauseView": "urn:li:fs_volunteerCauseView:ACoAAABZ9kgBnD4NsdiIMaVsiAQK3AwloLKM3Xk", "entityUrn": "urn:li:fs_profileView:ACoAAABZ9kgBnD4NsdiIMaVsiAQK3AwloLKM3Xk", "courseView": "urn:li:fs_courseView:ACoAAABZ9kgBnD4NsdiIMaVsiAQK3AwloLKM3Xk", "honorView": "urn:li:fs_honorView:ACoAAABZ9kgBnD4NsdiIMaVsiAQK3AwloLKM3Xk", "skillView": "urn:li:fs_skillView:ACoAAABZ9kgBnD4NsdiIMaVsiAQK3AwloLKM3Xk", "volunteerExperienceView": "urn:li:fs_volunteerExperienceView:ACoAAABZ9kgBnD4NsdiIMaVsiAQK3AwloLKM3Xk", "primaryLocale": "urn:li:fs_profileView:ACoAAABZ9kgBnD4NsdiIMaVsiAQK3AwloLKM3Xk,primaryLocale", "publicationView": "urn:li:fs_publicationView:ACoAAABZ9kgBnD4NsdiIMaVsiAQK3AwloLKM3Xk"}, "included": [{"$deletedFields": ["month", "day"], "year": 2004, "$type": "com.linkedin.common.Date", "$id": "urn:li:fs_position:(ACoAAABZ9kgBnD4NsdiIMaVsiAQK3AwloLKM3Xk,10463337),timePeriod,endDate"}, {"$deletedFields": ["month", "day"], "year": 2004, "$type": "com.linkedin.common.Date", "$id": "urn:li:fs_honor:(ACoAAABZ9kgBnD4NsdiIMaVsiAQK3AwloLKM3Xk,1649628655),issueDate"}, {"$deletedFields": ["month", "day"], "year": 2012, "$type": "com.linkedin.common.Date", "$id": "urn:li:fs_position:(ACoAAABZ9kgBnD4NsdiIMaVsiAQK3AwloLKM3Xk,318139490),timePeriod,endDate"}, {"$deletedFields": ["month", "day"], "year": 2006, "$type": "com.linkedin.common.Date", "$id": "urn:li:fs_position:(ACoAAABZ9kgBnD4NsdiIMaVsiAQK3AwloLKM3Xk,8273716),timePeriod,startDate"}, {"$deletedFields": ["month", "day"], "year": 2002, "$type": "com.linkedin.common.Date", "$id": "urn:li:fs_education:(ACoAAABZ9kgBnD4NsdiIMaVsiAQK3AwloLKM3Xk,4932084),timePeriod,startDate"}, {"$deletedFields": ["month", "day"], "year": 2004, "$type": "com.linkedin.common.Date", "$id": "urn:li:fs_education:(ACoAAABZ9kgBnD4NsdiIMaVsiAQK3AwloLKM3Xk,4932084),timePeriod,endDate"}, {"$deletedFields": ["month", "day"], "year": 2012, "$type": "com.linkedin.common.Date", "$id": "urn:li:fs_position:(ACoAAABZ9kgBnD4NsdiIMaVsiAQK3AwloLKM3Xk,8273716),timePeriod,endDate"}, {"$deletedFields": ["month", "day"], "year": 2002, "$type": "com.linkedin.common.Date", "$id": "urn:li:fs_honor:(ACoAAABZ9kgBnD4NsdiIMaVsiAQK3AwloLKM3Xk,1649570218),issueDate"}, {"$deletedFields": ["month", "day"], "year": 2004, "$type": "com.linkedin.common.Date", "$id": "urn:li:fs_position:(ACoAAABZ9kgBnD4NsdiIMaVsiAQK3AwloLKM3Xk,10463294),timePeriod,startDate"}, {"$deletedFields": ["month", "day"], "year": 2012, "$type": "com.linkedin.common.Date", "$id": "urn:li:fs_position:(ACoAAABZ9kgBnD4NsdiIMaVsiAQK3AwloLKM3Xk,318139490),timePeriod,startDate"}, {"$deletedFields": ["month", "day"], "year": 2013, "$type": "com.linkedin.common.Date", "$id": "urn:li:fs_position:(ACoAAABZ9kgBnD4NsdiIMaVsiAQK3AwloLKM3Xk,367088958),timePeriod,startDate"}, {"$deletedFields": ["month", "day"], "year": 1993, "$type": "com.linkedin.common.Date", "$id": "urn:li:fs_education:(ACoAAABZ9kgBnD4NsdiIMaVsiAQK3AwloLKM3Xk,2263923),timePeriod,startDate"}, {"$deletedFields": ["month", "day"], "year": 1998, "$type": "com.linkedin.common.Date", "$id": "urn:li:fs_education:(ACoAAABZ9kgBnD4NsdiIMaVsiAQK3AwloLKM3Xk,2263923),timePeriod,endDate"}, {"$deletedFields": ["month", "day"], "year": 2006, "$type": "com.linkedin.common.Date", "$id": "urn:li:fs_position:(ACoAAABZ9kgBnD4NsdiIMaVsiAQK3AwloLKM3Xk,10463294),timePeriod,endDate"}, {"$deletedFields": ["month", "day"], "year": 2004, "$type": "com.linkedin.common.Date", "$id": "urn:li:fs_position:(ACoAAABZ9kgBnD4NsdiIMaVsiAQK3AwloLKM3Xk,10463337),timePeriod,startDate"}, {"country": "US", "language": "en", "$deletedFields": ["variant"], "$type": "com.linkedin.common.Locale", "$id": "urn:li:fs_profile:ACoAAABZ9kgBnD4NsdiIMaVsiAQK3AwloLKM3Xk,supportedLocales,623f390b-4fa9-45f6-acd9-0932d1fbd911-0"}, {"country": "US", "$deletedFields": ["variant"], "language": "en", "$type": "com.linkedin.common.Locale", "$id": "urn:li:fs_profileView:ACoAAABZ9kgBnD4NsdiIMaVsiAQK3AwloLKM3Xk,primaryLocale"}, {"$deletedFields": [], "width": 200, "fileIdentifyingUrlPathSegment": "200_200/0?e=2123406000&v=beta&t=FM5UsKDroMiMDuNhqC4cvMtnRwwsyIq-fTtTQcF3HpU", "height": 200, "$type": "com.linkedin.common.VectorArtifact", "$id": "urn:li:fs_miniSchool:17926,logo,com.linkedin.common.VectorImage,artifacts,bc7285d3-1ae0-4291-b3de-99ac046aa2a2-0"}, {"$deletedFields": [], "width": 400, "fileIdentifyingUrlPathSegment": "400_400/0?e=2123406000&v=beta&t=2Lu95lhmE3xLERbBruupkzke9b_C5JnQFsCldWesJko", "height": 400, "$type": "com.linkedin.common.VectorArtifact", "$id": "urn:li:fs_miniCompany:164557,logo,com.linkedin.common.VectorImage,artifacts,31814be3-fc63-45cd-9c6c-b8d9df2242d8-2"}, {"$deletedFields": [], "width": 100, "fileIdentifyingUrlPathSegment": "100_100/0?e=2123406000&v=beta&t=WCKajgJ-xnXrA0iIyeMTmecCQ7Fw4kvero62qB8yDUc", "height": 100, "$type": "com.linkedin.common.VectorArtifact", "$id": "urn:li:fs_miniSchool:17926,logo,com.linkedin.common.VectorImage,artifacts,bc7285d3-1ae0-4291-b3de-99ac046aa2a2-1"}, {"$deletedFields": [], "width": 100, "fileIdentifyingUrlPathSegment": "100_100/0?e=2123406000&v=beta&t=pUuIRjW-K1U1XVnM0AGufiBxfF6xvOPZTm9DooHdM58", "height": 100, "$type": "com.linkedin.common.VectorArtifact", "$id": "urn:li:fs_miniCompany:164557,logo,com.linkedin.common.VectorImage,artifacts,31814be3-fc63-45cd-9c6c-b8d9df2242d8-1"}, {"$deletedFields": [], "width": 400, "fileIdentifyingUrlPathSegment": "400_400/0?e=2123406000&v=beta&t=6sHW7hG70_Fp68cFj8-6Y7YSzKFIj1C6ZeMHEfwq-pw", "height": 400, "$type": "com.linkedin.common.VectorArtifact", "$id": "urn:li:fs_miniSchool:17926,logo,com.linkedin.common.VectorImage,artifacts,bc7285d3-1ae0-4291-b3de-99ac046aa2a2-2"}, {"$deletedFields": [], "width": 200, "fileIdentifyingUrlPathSegment": "200_200/0?e=2123406000&v=beta&t=qzwK9_FTTuTAemAEdOdtWrBd1GIF8VoFsMT_0cYylPg", "height": 200, "$type": "com.linkedin.common.VectorArtifact", "$id": "urn:li:fs_miniCompany:164557,logo,com.linkedin.common.VectorImage,artifacts,31814be3-fc63-45cd-9c6c-b8d9df2242d8-0"}, {"$deletedFields": [], "width": 400, "fileIdentifyingUrlPathSegment": "400_400/0?e=2123406000&v=beta&t=c2r7Yz9_c6xXq6ZbtlEA9s8mpY0CR9pO124rtzK5Ei4", "height": 400, "$type": "com.linkedin.common.VectorArtifact", "$id": "urn:li:fs_miniSchool:18633,logo,com.linkedin.common.VectorImage,artifacts,77d5ee30-4ef5-4d10-9d1c-74cbe29eee64-2"}, {"$deletedFields": [], "width": 100, "fileIdentifyingUrlPathSegment": "100_100/0?e=2123406000&v=beta&t=4RGFxHatxD8zczZW_szVhZyNjbLREsUk0ZZki0-0-Gk", "height": 100, "$type": "com.linkedin.common.VectorArtifact", "$id": "urn:li:fs_miniSchool:18633,logo,com.linkedin.common.VectorImage,artifacts,77d5ee30-4ef5-4d10-9d1c-74cbe29eee64-1"}, {"$deletedFields": [], "width": 200, "fileIdentifyingUrlPathSegment": "200_200/0?e=2123406000&v=beta&t=urL0zEVbKBuYsIHCep6bxVD4areiaQ2uu9xsu9ozYq8", "height": 200, "$type": "com.linkedin.common.VectorArtifact", "$id": "urn:li:fs_miniSchool:18633,logo,com.linkedin.common.VectorImage,artifacts,77d5ee30-4ef5-4d10-9d1c-74cbe29eee64-0"}, {"$deletedFields": [], "width": 400, "fileIdentifyingUrlPathSegment": "400_400/0?e=2123406000&v=beta&t=Kcc1T_Ty-iVGWcIYNy97PvLCqQts6ja-6rH3G1TBm8k", "height": 400, "$type": "com.linkedin.common.VectorArtifact", "$id": "urn:li:fs_miniCompany:3028,logo,com.linkedin.common.VectorImage,artifacts,de53cde5-cf9e-4679-baf4-69c58356423b-2"}, {"$deletedFields": [], "width": 200, "fileIdentifyingUrlPathSegment": "200_200/0?e=2123406000&v=beta&t=2sSYXOFvXVyt9clo3xTtActUJR_pzd9voSGfUoU9mcU", "height": 200, "$type": "com.linkedin.common.VectorArtifact", "$id": "urn:li:fs_miniCompany:3028,logo,com.linkedin.common.VectorImage,artifacts,de53cde5-cf9e-4679-baf4-69c58356423b-0"}, {"$deletedFields": [], "width": 100, "fileIdentifyingUrlPathSegment": "100_100/0?e=2123406000&v=beta&t=VmazsP5LxCqgcSJBG8oiE3Q5jWTj-DNd0Te_5sQA8c8", "height": 100, "$type": "com.linkedin.common.VectorArtifact", "$id": "urn:li:fs_miniCompany:3028,logo,com.linkedin.common.VectorImage,artifacts,de53cde5-cf9e-4679-baf4-69c58356423b-1"}, {"$deletedFields": ["attribution"], "artifacts": ["urn:li:fs_miniCompany:3028,logo,com.linkedin.common.VectorImage,artifacts,de53cde5-cf9e-4679-baf4-69c58356423b-0", "urn:li:fs_miniCompany:3028,logo,com.linkedin.common.VectorImage,artifacts,de53cde5-cf9e-4679-baf4-69c58356423b-1", "urn:li:fs_miniCompany:3028,logo,com.linkedin.common.VectorImage,artifacts,de53cde5-cf9e-4679-baf4-69c58356423b-2"], "rootUrl": "https://media.licdn.com/dms/image/C4E0BAQEQLo6jPY08UA/company-logo_", "$type": "com.linkedin.common.VectorImage", "$id": "urn:li:fs_miniCompany:3028,logo,com.linkedin.common.VectorImage"}, {"$deletedFields": ["attribution"], "artifacts": ["urn:li:fs_miniSchool:17926,logo,com.linkedin.common.VectorImage,artifacts,bc7285d3-1ae0-4291-b3de-99ac046aa2a2-0", "urn:li:fs_miniSchool:17926,logo,com.linkedin.common.VectorImage,artifacts,bc7285d3-1ae0-4291-b3de-99ac046aa2a2-1", "urn:li:fs_miniSchool:17926,logo,com.linkedin.common.VectorImage,artifacts,bc7285d3-1ae0-4291-b3de-99ac046aa2a2-2"], "rootUrl": "https://media.licdn.com/dms/image/C4D0BAQFVZxF7TIA0Ug/company-logo_", "$type": "com.linkedin.common.VectorImage", "$id": "urn:li:fs_miniSchool:17926,logo,com.linkedin.common.VectorImage"}, {"$deletedFields": ["attribution"], "artifacts": ["urn:li:fs_miniSchool:18633,logo,com.linkedin.common.VectorImage,artifacts,77d5ee30-4ef5-4d10-9d1c-74cbe29eee64-0", "urn:li:fs_miniSchool:18633,logo,com.linkedin.common.VectorImage,artifacts,77d5ee30-4ef5-4d10-9d1c-74cbe29eee64-1", "urn:li:fs_miniSchool:18633,logo,com.linkedin.common.VectorImage,artifacts,77d5ee30-4ef5-4d10-9d1c-74cbe29eee64-2"], "rootUrl": "https://media.licdn.com/dms/image/C4E0BAQFGfERBPGurCg/company-logo_", "$type": "com.linkedin.common.VectorImage", "$id": "urn:li:fs_miniSchool:18633,logo,com.linkedin.common.VectorImage"}, {"$deletedFields": ["attribution"], "artifacts": ["urn:li:fs_miniCompany:164557,logo,com.linkedin.common.VectorImage,artifacts,31814be3-fc63-45cd-9c6c-b8d9df2242d8-0", "urn:li:fs_miniCompany:164557,logo,com.linkedin.common.VectorImage,artifacts,31814be3-fc63-45cd-9c6c-b8d9df2242d8-1", "urn:li:fs_miniCompany:164557,logo,com.linkedin.common.VectorImage,artifacts,31814be3-fc63-45cd-9c6c-b8d9df2242d8-2"], "rootUrl": "https://media.licdn.com/dms/image/C4E0BAQEgt2hYZAC_Yw/company-logo_", "$type": "com.linkedin.common.VectorImage", "$id": "urn:li:fs_miniCompany:164557,logo,com.linkedin.common.VectorImage"}, {"total": 0, "$deletedFields": [], "start": 0, "count": 10, "links": [], "$type": "com.linkedin.restli.common.CollectionMetadata", "$id": "urn:li:fs_patentView:ACoAAABZ9kgBnD4NsdiIMaVsiAQK3AwloLKM3Xk,paging"}, {"total": 0, "$deletedFields": [], "start": 0, "count": 10, "links": [], "$type": "com.linkedin.restli.common.CollectionMetadata", "$id": "urn:li:fs_testScoreView:ACoAAABZ9kgBnD4NsdiIMaVsiAQK3AwloLKM3Xk,paging"}, {"total": 7, "$deletedFields": [], "start": 0, "count": 5, "links": [], "$type": "com.linkedin.restli.common.CollectionMetadata", "$id": "urn:li:fs_positionView:ACoAAABZ9kgBnD4NsdiIMaVsiAQK3AwloLKM3Xk,paging"}, {"total": 2, "$deletedFields": [], "start": 0, "count": 10, "links": [], "$type": "com.linkedin.restli.common.CollectionMetadata", "$id": "urn:li:fs_honorView:ACoAAABZ9kgBnD4NsdiIMaVsiAQK3AwloLKM3Xk,paging"}, {"total": 36, "$deletedFields": [], "start": 0, "count": 4, "links": [], "$type": "com.linkedin.restli.common.CollectionMetadata", "$id": "urn:li:fs_skillView:ACoAAABZ9kgBnD4NsdiIMaVsiAQK3AwloLKM3Xk,paging"}, {"total": 0, "$deletedFields": [], "start": 0, "count": 3, "links": [], "$type": "com.linkedin.restli.common.CollectionMetadata", "$id": "urn:li:fs_volunteerExperienceView:ACoAAABZ9kgBnD4NsdiIMaVsiAQK3AwloLKM3Xk,paging"}, {"total": 1, "$deletedFields": [], "start": 0, "count": 10, "links": [], "$type": "com.linkedin.restli.common.CollectionMetadata", "$id": "urn:li:fs_languageView:ACoAAABZ9kgBnD4NsdiIMaVsiAQK3AwloLKM3Xk,paging"}, {"total": 0, "$deletedFields": [], "start": 0, "count": 10, "links": [], "$type": "com.linkedin.restli.common.CollectionMetadata", "$id": "urn:li:fs_certificationView:ACoAAABZ9kgBnD4NsdiIMaVsiAQK3AwloLKM3Xk,paging"}, {"total": 0, "$deletedFields": [], "start": 0, "count": 10, "links": [], "$type": "com.linkedin.restli.common.CollectionMetadata", "$id": "urn:li:fs_publicationView:ACoAAABZ9kgBnD4NsdiIMaVsiAQK3AwloLKM3Xk,paging"}, {"total": 1, "$deletedFields": [], "start": 0, "count": 10, "links": [], "$type": "com.linkedin.restli.common.CollectionMetadata", "$id": "urn:li:fs_projectView:ACoAAABZ9kgBnD4NsdiIMaVsiAQK3AwloLKM3Xk,paging"}, {"total": 0, "$deletedFields": [], "start": 0, "count": 10, "links": [], "$type": "com.linkedin.restli.common.CollectionMetadata", "$id": "urn:li:fs_courseView:ACoAAABZ9kgBnD4NsdiIMaVsiAQK3AwloLKM3Xk,paging"}, {"total": 2, "$deletedFields": [], "start": 0, "count": 3, "links": [], "$type": "com.linkedin.restli.common.CollectionMetadata", "$id": "urn:li:fs_educationView:ACoAAABZ9kgBnD4NsdiIMaVsiAQK3AwloLKM3Xk,paging"}, {"total": 0, "$deletedFields": [], "start": 0, "count": 0, "links": [], "$type": "com.linkedin.restli.common.CollectionMetadata", "$id": "urn:li:fs_volunteerCauseView:ACoAAABZ9kgBnD4NsdiIMaVsiAQK3AwloLKM3Xk,paging"}, {"total": 0, "$deletedFields": [], "start": 0, "count": 10, "links": [], "$type": "com.linkedin.restli.common.CollectionMetadata", "$id": "urn:li:fs_organizationView:ACoAAABZ9kgBnD4NsdiIMaVsiAQK3AwloLKM3Xk,paging"}, {"$deletedFields": ["endDate"], "startDate": "urn:li:fs_position:(ACoAAABZ9kgBnD4NsdiIMaVsiAQK3AwloLKM3Xk,367088958),timePeriod,startDate", "$type": "com.linkedin.voyager.common.DateRange", "$id": "urn:li:fs_position:(ACoAAABZ9kgBnD4NsdiIMaVsiAQK3AwloLKM3Xk,367088958),timePeriod"}, {"$deletedFields": [], "endDate": "urn:li:fs_position:(ACoAAABZ9kgBnD4NsdiIMaVsiAQK3AwloLKM3Xk,8273716),timePeriod,endDate", "startDate": "urn:li:fs_position:(ACoAAABZ9kgBnD4NsdiIMaVsiAQK3AwloLKM3Xk,8273716),timePeriod,startDate", "$type": "com.linkedin.voyager.common.DateRange", "$id": "urn:li:fs_position:(ACoAAABZ9kgBnD4NsdiIMaVsiAQK3AwloLKM3Xk,8273716),timePeriod"}, {"$deletedFields": [], "endDate": "urn:li:fs_position:(ACoAAABZ9kgBnD4NsdiIMaVsiAQK3AwloLKM3Xk,10463294),timePeriod,endDate", "startDate": "urn:li:fs_position:(ACoAAABZ9kgBnD4NsdiIMaVsiAQK3AwloLKM3Xk,10463294),timePeriod,startDate", "$type": "com.linkedin.voyager.common.DateRange", "$id": "urn:li:fs_position:(ACoAAABZ9kgBnD4NsdiIMaVsiAQK3AwloLKM3Xk,10463294),timePeriod"}, {"$deletedFields": [], "endDate": "urn:li:fs_education:(ACoAAABZ9kgBnD4NsdiIMaVsiAQK3AwloLKM3Xk,2263923),timePeriod,endDate", "startDate": "urn:li:fs_education:(ACoAAABZ9kgBnD4NsdiIMaVsiAQK3AwloLKM3Xk,2263923),timePeriod,startDate", "$type": "com.linkedin.voyager.common.DateRange", "$id": "urn:li:fs_education:(ACoAAABZ9kgBnD4NsdiIMaVsiAQK3AwloLKM3Xk,2263923),timePeriod"}, {"$deletedFields": [], "endDate": "urn:li:fs_position:(ACoAAABZ9kgBnD4NsdiIMaVsiAQK3AwloLKM3Xk,10463337),timePeriod,endDate", "startDate": "urn:li:fs_position:(ACoAAABZ9kgBnD4NsdiIMaVsiAQK3AwloLKM3Xk,10463337),timePeriod,startDate", "$type": "com.linkedin.voyager.common.DateRange", "$id": "urn:li:fs_position:(ACoAAABZ9kgBnD4NsdiIMaVsiAQK3AwloLKM3Xk,10463337),timePeriod"}, {"$deletedFields": [], "endDate": "urn:li:fs_education:(ACoAAABZ9kgBnD4NsdiIMaVsiAQK3AwloLKM3Xk,4932084),timePeriod,endDate", "startDate": "urn:li:fs_education:(ACoAAABZ9kgBnD4NsdiIMaVsiAQK3AwloLKM3Xk,4932084),timePeriod,startDate", "$type": "com.linkedin.voyager.common.DateRange", "$id": "urn:li:fs_education:(ACoAAABZ9kgBnD4NsdiIMaVsiAQK3AwloLKM3Xk,4932084),timePeriod"}, {"$deletedFields": [], "endDate": "urn:li:fs_position:(ACoAAABZ9kgBnD4NsdiIMaVsiAQK3AwloLKM3Xk,318139490),timePeriod,endDate", "startDate": "urn:li:fs_position:(ACoAAABZ9kgBnD4NsdiIMaVsiAQK3AwloLKM3Xk,318139490),timePeriod,startDate", "$type": "com.linkedin.voyager.common.DateRange", "$id": "urn:li:fs_position:(ACoAAABZ9kgBnD4NsdiIMaVsiAQK3AwloLKM3Xk,318139490),timePeriod"}, {"$deletedFields": [], "countryCode": "us", "postalCode": "19122", "$type": "com.linkedin.voyager.common.NormBasicLocation", "$id": "urn:li:fs_profile:ACoAAABZ9kgBnD4NsdiIMaVsiAQK3AwloLKM3Xk,location,basicLocation"}, {"$deletedFields": ["universalName"], "objectUrn": "urn:li:company:3028", "entityUrn": "urn:li:fs_miniCompany:3028", "name": "University of California, San Francisco", "showcase": false, "active": true, "logo": {"com.linkedin.common.VectorImage": "urn:li:fs_miniCompany:3028,logo,com.linkedin.common.VectorImage"}, "trackingId": "KYZHMY1gSrquXRI9U2b79w==", "$type": "com.linkedin.voyager.entities.shared.MiniCompany"}, {"$deletedFields": ["universalName"], "objectUrn": "urn:li:company:164557", "entityUrn": "urn:li:fs_miniCompany:164557", "name": "JSTOR", "showcase": false, "active": true, "logo": {"com.linkedin.common.VectorImage": "urn:li:fs_miniCompany:164557,logo,com.linkedin.common.VectorImage"}, "trackingId": "LCd0aM/JTmmB653wpRcAqQ==", "$type": "com.linkedin.voyager.entities.shared.MiniCompany"}, {"$deletedFields": [], "objectUrn": "urn:li:school:17926", "entityUrn": "urn:li:fs_miniSchool:17926", "active": true, "logo": {"com.linkedin.common.VectorImage": "urn:li:fs_miniSchool:17926,logo,com.linkedin.common.VectorImage"}, "schoolName": "Stanford University", "trackingId": "jILd52BxTJ+qLIv7hY5SPw==", "$type": "com.linkedin.voyager.entities.shared.MiniSchool"}, {"$deletedFields": [], "objectUrn": "urn:li:school:18633", "entityUrn": "urn:li:fs_miniSchool:18633", "active": true, "logo": {"com.linkedin.common.VectorImage": "urn:li:fs_miniSchool:18633,logo,com.linkedin.common.VectorImage"}, "schoolName": "University of Michigan", "trackingId": "UhW8XyiERfmeUw4/EkI8Rw==", "$type": "com.linkedin.voyager.entities.shared.MiniSchool"}, {"$deletedFields": [], "entityUrn": "urn:li:fs_certificationView:ACoAAABZ9kgBnD4NsdiIMaVsiAQK3AwloLKM3Xk", "profileId": "ACoAAABZ9kgBnD4NsdiIMaVsiAQK3AwloLKM3Xk", "elements": [], "paging": "urn:li:fs_certificationView:ACoAAABZ9kgBnD4NsdiIMaVsiAQK3AwloLKM3Xk,paging", "$type": "com.linkedin.voyager.identity.profile.CertificationView"}, {"$deletedFields": ["name"], "entityUrn": "urn:li:fs_contributor:(ACoAAABZ9kgBnD4NsdiIMaVsiAQK3AwloLKM3Xk,19,20)", "member": "urn:li:fs_miniProfile:ACoAAABZ9kgBnD4NsdiIMaVsiAQK3AwloLKM3Xk", "profileUrn": "urn:li:fs_miniProfile:ACoAAABZ9kgBnD4NsdiIMaVsiAQK3AwloLKM3Xk", "$type": "com.linkedin.voyager.identity.profile.Contributor"}, {"$deletedFields": [], "entityUrn": "urn:li:fs_courseView:ACoAAABZ9kgBnD4NsdiIMaVsiAQK3AwloLKM3Xk", "profileId": "ACoAAABZ9kgBnD4NsdiIMaVsiAQK3AwloLKM3Xk", "elements": [], "paging": "urn:li:fs_courseView:ACoAAABZ9kgBnD4NsdiIMaVsiAQK3AwloLKM3Xk,paging", "$type": "com.linkedin.voyager.identity.profile.CourseView"}, {"$deletedFields": ["courses", "projects", "description", "recommendations", "honors", "entityLocale", "activities", "grade", "fieldOfStudyUrn", "testScores", "degreeUrn"], "entityUrn": "urn:li:fs_education:(ACoAAABZ9kgBnD4NsdiIMaVsiAQK3AwloLKM3Xk,2263923)", "school": "urn:li:fs_miniSchool:17926", "timePeriod": "urn:li:fs_education:(ACoAAABZ9kgBnD4NsdiIMaVsiAQK3AwloLKM3Xk,2263923),timePeriod", "degreeName": "Bachelor of Arts (B.A.)", "schoolName": "Stanford University", "fieldOfStudy": "History", "schoolUrn": "urn:li:fs_miniSchool:17926", "$type": "com.linkedin.voyager.identity.profile.Education"}, {"$deletedFields": ["courses", "projects", "description", "recommendations", "entityLocale", "activities", "grade", "fieldOfStudyUrn", "testScores", "degreeUrn"], "entityUrn": "urn:li:fs_education:(ACoAAABZ9kgBnD4NsdiIMaVsiAQK3AwloLKM3Xk,4932084)", "school": "urn:li:fs_miniSchool:18633", "timePeriod": "urn:li:fs_education:(ACoAAABZ9kgBnD4NsdiIMaVsiAQK3AwloLKM3Xk,4932084),timePeriod", "degreeName": "MIS", "schoolName": "University of Michigan", "fieldOfStudy": "School of Information", "honors": ["urn:li:fs_honor:(ACoAAABZ9kgBnD4NsdiIMaVsiAQK3AwloLKM3Xk,1649570218)", "urn:li:fs_honor:(ACoAAABZ9kgBnD4NsdiIMaVsiAQK3AwloLKM3Xk,1649628655)"], "schoolUrn": "urn:li:fs_miniSchool:18633", "$type": "com.linkedin.voyager.identity.profile.Education"}, {"$deletedFields": [], "entityUrn": "urn:li:fs_educationView:ACoAAABZ9kgBnD4NsdiIMaVsiAQK3AwloLKM3Xk", "profileId": "ACoAAABZ9kgBnD4NsdiIMaVsiAQK3AwloLKM3Xk", "elements": ["urn:li:fs_education:(ACoAAABZ9kgBnD4NsdiIMaVsiAQK3AwloLKM3Xk,4932084)", "urn:li:fs_education:(ACoAAABZ9kgBnD4NsdiIMaVsiAQK3AwloLKM3Xk,2263923)"], "paging": "urn:li:fs_educationView:ACoAAABZ9kgBnD4NsdiIMaVsiAQK3AwloLKM3Xk,paging", "$type": "com.linkedin.voyager.identity.profile.EducationView"}, {"$deletedFields": [], "start": 201, "end": 500, "$type": "com.linkedin.voyager.identity.profile.EmployeeCountRange", "$id": "urn:li:fs_position:(ACoAAABZ9kgBnD4NsdiIMaVsiAQK3AwloLKM3Xk,10463337),company,employeeCountRange"}, {"$deletedFields": ["end"], "start": 10001, "$type": "com.linkedin.voyager.identity.profile.EmployeeCountRange", "$id": "urn:li:fs_position:(ACoAAABZ9kgBnD4NsdiIMaVsiAQK3AwloLKM3Xk,8273716),company,employeeCountRange"}, {"$deletedFields": ["description"], "occupation": "urn:li:fs_education:(ACoAAABZ9kgBnD4NsdiIMaVsiAQK3AwloLKM3Xk,4932084)", "entityUrn": "urn:li:fs_honor:(ACoAAABZ9kgBnD4NsdiIMaVsiAQK3AwloLKM3Xk,1649628655)", "title": "Harold T. Pinkett Minority Student Award", "issueDate": "urn:li:fs_honor:(ACoAAABZ9kgBnD4NsdiIMaVsiAQK3AwloLKM3Xk,1649628655),issueDate", "issuer": "Society of American Archivists", "$type": "com.linkedin.voyager.identity.profile.Honor"}, {"$deletedFields": ["description"], "occupation": "urn:li:fs_education:(ACoAAABZ9kgBnD4NsdiIMaVsiAQK3AwloLKM3Xk,4932084)", "entityUrn": "urn:li:fs_honor:(ACoAAABZ9kgBnD4NsdiIMaVsiAQK3AwloLKM3Xk,1649570218)", "title": "Spectrum Scholarship", "issueDate": "urn:li:fs_honor:(ACoAAABZ9kgBnD4NsdiIMaVsiAQK3AwloLKM3Xk,1649570218),issueDate", "issuer": "American Library Association", "$type": "com.linkedin.voyager.identity.profile.Honor"}, {"$deletedFields": [], "entityUrn": "urn:li:fs_honorView:ACoAAABZ9kgBnD4NsdiIMaVsiAQK3AwloLKM3Xk", "profileId": "ACoAAABZ9kgBnD4NsdiIMaVsiAQK3AwloLKM3Xk", "elements": ["urn:li:fs_honor:(ACoAAABZ9kgBnD4NsdiIMaVsiAQK3AwloLKM3Xk,1649628655)", "urn:li:fs_honor:(ACoAAABZ9kgBnD4NsdiIMaVsiAQK3AwloLKM3Xk,1649570218)"], "paging": "urn:li:fs_honorView:ACoAAABZ9kgBnD4NsdiIMaVsiAQK3AwloLKM3Xk,paging", "$type": "com.linkedin.voyager.identity.profile.HonorView"}, {"$deletedFields": ["proficiency"], "entityUrn": "urn:li:fs_language:(ACoAAABZ9kgBnD4NsdiIMaVsiAQK3AwloLKM3Xk,18)", "name": "Spanish", "$type": "com.linkedin.voyager.identity.profile.Language"}, {"$deletedFields": [], "entityUrn": "urn:li:fs_languageView:ACoAAABZ9kgBnD4NsdiIMaVsiAQK3AwloLKM3Xk", "profileId": "ACoAAABZ9kgBnD4NsdiIMaVsiAQK3AwloLKM3Xk", "elements": ["urn:li:fs_language:(ACoAAABZ9kgBnD4NsdiIMaVsiAQK3AwloLKM3Xk,18)"], "paging": "urn:li:fs_languageView:ACoAAABZ9kgBnD4NsdiIMaVsiAQK3AwloLKM3Xk,paging", "$type": "com.linkedin.voyager.identity.profile.LanguageView"}, {"$deletedFields": [], "entityUrn": "urn:li:fs_organizationView:ACoAAABZ9kgBnD4NsdiIMaVsiAQK3AwloLKM3Xk", "profileId": "ACoAAABZ9kgBnD4NsdiIMaVsiAQK3AwloLKM3Xk", "elements": [], "paging": "urn:li:fs_organizationView:ACoAAABZ9kgBnD4NsdiIMaVsiAQK3AwloLKM3Xk,paging", "$type": "com.linkedin.voyager.identity.profile.OrganizationView"}, {"$deletedFields": [], "entityUrn": "urn:li:fs_patentView:ACoAAABZ9kgBnD4NsdiIMaVsiAQK3AwloLKM3Xk", "profileId": "ACoAAABZ9kgBnD4NsdiIMaVsiAQK3AwloLKM3Xk", "elements": [], "paging": "urn:li:fs_patentView:ACoAAABZ9kgBnD4NsdiIMaVsiAQK3AwloLKM3Xk,paging", "$type": "com.linkedin.voyager.identity.profile.PatentView"}, {"$deletedFields": ["courses", "locationName", "projects", "description", "companyUrn", "recommendations", "honors", "entityLocale", "organizations", "company", "region"], "entityUrn": "urn:li:fs_position:(ACoAAABZ9kgBnD4NsdiIMaVsiAQK3AwloLKM3Xk,10463294)", "companyName": "AIDS Epidemic Historical Records Project", "timePeriod": "urn:li:fs_position:(ACoAAABZ9kgBnD4NsdiIMaVsiAQK3AwloLKM3Xk,10463294),timePeriod", "title": "Archivist", "$type": "com.linkedin.voyager.identity.profile.Position"}, {"$deletedFields": ["courses", "locationName", "projects", "description", "recommendations", "honors", "entityLocale", "organizations", "region"], "entityUrn": "urn:li:fs_position:(ACoAAABZ9kgBnD4NsdiIMaVsiAQK3AwloLKM3Xk,10463337)", "companyName": "JSTOR", "timePeriod": "urn:li:fs_position:(ACoAAABZ9kgBnD4NsdiIMaVsiAQK3AwloLKM3Xk,10463337),timePeriod", "company": "urn:li:fs_position:(ACoAAABZ9kgBnD4NsdiIMaVsiAQK3AwloLKM3Xk,10463337),company", "title": "Production Assistant", "companyUrn": "urn:li:fs_miniCompany:164557", "$type": "com.linkedin.voyager.identity.profile.Position"}, {"$deletedFields": ["courses", "locationName", "projects", "description", "companyUrn", "recommendations", "honors", "entityLocale", "organizations", "company", "region"], "entityUrn": "urn:li:fs_position:(ACoAAABZ9kgBnD4NsdiIMaVsiAQK3AwloLKM3Xk,318139490)", "companyName": "Medical Center Archives, New York-Presbyterian Hospital Weill-Cornell Medical College", "timePeriod": "urn:li:fs_position:(ACoAAABZ9kgBnD4NsdiIMaVsiAQK3AwloLKM3Xk,318139490),timePeriod", "title": "Project Archivist", "$type": "com.linkedin.voyager.identity.profile.Position"}, {"$deletedFields": ["courses", "locationName", "description", "recommendations", "honors", "entityLocale", "organizations", "region"], "projects": ["urn:li:fs_project:(ACoAAABZ9kgBnD4NsdiIMaVsiAQK3AwloLKM3Xk,19)"], "entityUrn": "urn:li:fs_position:(ACoAAABZ9kgBnD4NsdiIMaVsiAQK3AwloLKM3Xk,8273716)", "companyName": "University of California at San Francisco", "timePeriod": "urn:li:fs_position:(ACoAAABZ9kgBnD4NsdiIMaVsiAQK3AwloLKM3Xk,8273716),timePeriod", "company": "urn:li:fs_position:(ACoAAABZ9kgBnD4NsdiIMaVsiAQK3AwloLKM3Xk,8273716),company", "title": "Assistant Archivist, Acting Manager, Archives and Special Collections", "companyUrn": "urn:li:fs_miniCompany:3028", "$type": "com.linkedin.voyager.identity.profile.Position"}, {"$deletedFields": ["courses", "projects", "description", "companyUrn", "recommendations", "honors", "entityLocale", "organizations", "company", "region"], "locationName": "Philadelphia", "entityUrn": "urn:li:fs_position:(ACoAAABZ9kgBnD4NsdiIMaVsiAQK3AwloLKM3Xk,367088958)", "companyName": "Temple University Libraries", "timePeriod": "urn:li:fs_position:(ACoAAABZ9kgBnD4NsdiIMaVsiAQK3AwloLKM3Xk,367088958),timePeriod", "title": "Librarian and Coordinator of Public Services & Outreach, Special Collections Research Center", "$type": "com.linkedin.voyager.identity.profile.Position"}, {"employeeCountRange": "urn:li:fs_position:(ACoAAABZ9kgBnD4NsdiIMaVsiAQK3AwloLKM3Xk,8273716),company,employeeCountRange", "$deletedFields": [], "miniCompany": "urn:li:fs_miniCompany:3028", "industries": ["Higher Education"], "$type": "com.linkedin.voyager.identity.profile.PositionCompany", "$id": "urn:li:fs_position:(ACoAAABZ9kgBnD4NsdiIMaVsiAQK3AwloLKM3Xk,8273716),company"}, {"employeeCountRange": "urn:li:fs_position:(ACoAAABZ9kgBnD4NsdiIMaVsiAQK3AwloLKM3Xk,10463337),company,employeeCountRange", "$deletedFields": [], "miniCompany": "urn:li:fs_miniCompany:164557", "industries": ["Higher Education"], "$type": "com.linkedin.voyager.identity.profile.PositionCompany", "$id": "urn:li:fs_position:(ACoAAABZ9kgBnD4NsdiIMaVsiAQK3AwloLKM3Xk,10463337),company"}, {"$deletedFields": [], "entityUrn": "urn:li:fs_positionView:ACoAAABZ9kgBnD4NsdiIMaVsiAQK3AwloLKM3Xk", "profileId": "ACoAAABZ9kgBnD4NsdiIMaVsiAQK3AwloLKM3Xk", "elements": ["urn:li:fs_position:(ACoAAABZ9kgBnD4NsdiIMaVsiAQK3AwloLKM3Xk,367088958)", "urn:li:fs_position:(ACoAAABZ9kgBnD4NsdiIMaVsiAQK3AwloLKM3Xk,318139490)", "urn:li:fs_position:(ACoAAABZ9kgBnD4NsdiIMaVsiAQK3AwloLKM3Xk,8273716)", "urn:li:fs_position:(ACoAAABZ9kgBnD4NsdiIMaVsiAQK3AwloLKM3Xk,10463294)", "urn:li:fs_position:(ACoAAABZ9kgBnD4NsdiIMaVsiAQK3AwloLKM3Xk,10463337)"], "paging": "urn:li:fs_positionView:ACoAAABZ9kgBnD4NsdiIMaVsiAQK3AwloLKM3Xk,paging", "$type": "com.linkedin.voyager.identity.profile.PositionView"}, {"industryName": "Libraries", "lastName": "Hurtado", "supportedLocales": ["urn:li:fs_profile:ACoAAABZ9kgBnD4NsdiIMaVsiAQK3AwloLKM3Xk,supportedLocales,623f390b-4fa9-45f6-acd9-0932d1fbd911-0"], "locationName": "Philadelphia, Pennsylvania", "versionTag": "260168167", "industryUrn": "urn:li:fs_industry:85", "$type": "com.linkedin.voyager.identity.profile.Profile", "defaultLocale": "urn:li:fs_profileView:ACoAAABZ9kgBnD4NsdiIMaVsiAQK3AwloLKM3Xk,primaryLocale", "firstName": "Josue", "$deletedFields": ["backgroundImage", "maidenName", "phoneticLastName", "contactInstructions", "entityLocale", "state", "phoneticFirstName", "summary", "address", "pictureInfo", "profilePictureOriginalImage", "birthDate", "profilePicture", "interests", "backgroundPicture", "backgroundPictureOriginalImage"], "showEducationOnProfileTopCard": true, "entityUrn": "urn:li:fs_profile:ACoAAABZ9kgBnD4NsdiIMaVsiAQK3AwloLKM3Xk", "location": "urn:li:fs_profile:ACoAAABZ9kgBnD4NsdiIMaVsiAQK3AwloLKM3Xk,location", "miniProfile": "urn:li:fs_miniProfile:ACoAAABZ9kgBnD4NsdiIMaVsiAQK3AwloLKM3Xk", "headline": "Librarian, Coordinator of Public Services & Outreach, Special Collections Research Center at Temple University Libraries"}, {"$deletedFields": [], "basicLocation": "urn:li:fs_profile:ACoAAABZ9kgBnD4NsdiIMaVsiAQK3AwloLKM3Xk,location,basicLocation", "preferredGeoPlace": "urn:li:fs_city:(us,3-3-0-51-1)", "$type": "com.linkedin.voyager.identity.profile.ProfileLocation", "$id": "urn:li:fs_profile:ACoAAABZ9kgBnD4NsdiIMaVsiAQK3AwloLKM3Xk,location"}, {"$deletedFields": ["timePeriod"], "occupation": "urn:li:fs_position:(ACoAAABZ9kgBnD4NsdiIMaVsiAQK3AwloLKM3Xk,8273716)", "entityUrn": "urn:li:fs_project:(ACoAAABZ9kgBnD4NsdiIMaVsiAQK3AwloLKM3Xk,19)", "members": ["urn:li:fs_contributor:(ACoAAABZ9kgBnD4NsdiIMaVsiAQK3AwloLKM3Xk,19,20)"], "description": "A History of Medicine Libguide", "title": "Libguide", "url": "http://guides.library.ucsf.edu/homeopathy", "$type": "com.linkedin.voyager.identity.profile.Project"}, {"$deletedFields": [], "entityUrn": "urn:li:fs_projectView:ACoAAABZ9kgBnD4NsdiIMaVsiAQK3AwloLKM3Xk", "profileId": "ACoAAABZ9kgBnD4NsdiIMaVsiAQK3AwloLKM3Xk", "elements": ["urn:li:fs_project:(ACoAAABZ9kgBnD4NsdiIMaVsiAQK3AwloLKM3Xk,19)"], "paging": "urn:li:fs_projectView:ACoAAABZ9kgBnD4NsdiIMaVsiAQK3AwloLKM3Xk,paging", "$type": "com.linkedin.voyager.identity.profile.ProjectView"}, {"$deletedFields": [], "entityUrn": "urn:li:fs_publicationView:ACoAAABZ9kgBnD4NsdiIMaVsiAQK3AwloLKM3Xk", "profileId": "ACoAAABZ9kgBnD4NsdiIMaVsiAQK3AwloLKM3Xk", "elements": [], "paging": "urn:li:fs_publicationView:ACoAAABZ9kgBnD4NsdiIMaVsiAQK3AwloLKM3Xk,paging", "$type": "com.linkedin.voyager.identity.profile.PublicationView"}, {"$deletedFields": ["standardizedSkillUrn", "standardizedSkill"], "entityUrn": "urn:li:fs_skill:(ACoAAABZ9kgBnD4NsdiIMaVsiAQK3AwloLKM3Xk,56)", "name": "Public Services", "$type": "com.linkedin.voyager.identity.profile.Skill"}, {"$deletedFields": ["standardizedSkillUrn", "standardizedSkill"], "entityUrn": "urn:li:fs_skill:(ACoAAABZ9kgBnD4NsdiIMaVsiAQK3AwloLKM3Xk,53)", "name": "Archives", "$type": "com.linkedin.voyager.identity.profile.Skill"}, {"$deletedFields": ["standardizedSkillUrn", "standardizedSkill"], "entityUrn": "urn:li:fs_skill:(ACoAAABZ9kgBnD4NsdiIMaVsiAQK3AwloLKM3Xk,54)", "name": "Special Collections", "$type": "com.linkedin.voyager.identity.profile.Skill"}, {"$deletedFields": ["standardizedSkillUrn", "standardizedSkill"], "entityUrn": "urn:li:fs_skill:(ACoAAABZ9kgBnD4NsdiIMaVsiAQK3AwloLKM3Xk,55)", "name": "Library", "$type": "com.linkedin.voyager.identity.profile.Skill"}, {"$deletedFields": [], "entityUrn": "urn:li:fs_skillView:ACoAAABZ9kgBnD4NsdiIMaVsiAQK3AwloLKM3Xk", "profileId": "ACoAAABZ9kgBnD4NsdiIMaVsiAQK3AwloLKM3Xk", "elements": ["urn:li:fs_skill:(ACoAAABZ9kgBnD4NsdiIMaVsiAQK3AwloLKM3Xk,53)", "urn:li:fs_skill:(ACoAAABZ9kgBnD4NsdiIMaVsiAQK3AwloLKM3Xk,54)", "urn:li:fs_skill:(ACoAAABZ9kgBnD4NsdiIMaVsiAQK3AwloLKM3Xk,55)", "urn:li:fs_skill:(ACoAAABZ9kgBnD4NsdiIMaVsiAQK3AwloLKM3Xk,56)"], "paging": "urn:li:fs_skillView:ACoAAABZ9kgBnD4NsdiIMaVsiAQK3AwloLKM3Xk,paging", "$type": "com.linkedin.voyager.identity.profile.SkillView"}, {"$deletedFields": [], "entityUrn": "urn:li:fs_testScoreView:ACoAAABZ9kgBnD4NsdiIMaVsiAQK3AwloLKM3Xk", "profileId": "ACoAAABZ9kgBnD4NsdiIMaVsiAQK3AwloLKM3Xk", "elements": [], "paging": "urn:li:fs_testScoreView:ACoAAABZ9kgBnD4NsdiIMaVsiAQK3AwloLKM3Xk,paging", "$type": "com.linkedin.voyager.identity.profile.TestScoreView"}, {"$deletedFields": [], "entityUrn": "urn:li:fs_volunteerCauseView:ACoAAABZ9kgBnD4NsdiIMaVsiAQK3AwloLKM3Xk", "profileId": "ACoAAABZ9kgBnD4NsdiIMaVsiAQK3AwloLKM3Xk", "elements": [], "paging": "urn:li:fs_volunteerCauseView:ACoAAABZ9kgBnD4NsdiIMaVsiAQK3AwloLKM3Xk,paging", "$type": "com.linkedin.voyager.identity.profile.VolunteerCauseView"}, {"$deletedFields": [], "entityUrn": "urn:li:fs_volunteerExperienceView:ACoAAABZ9kgBnD4NsdiIMaVsiAQK3AwloLKM3Xk", "profileId": "ACoAAABZ9kgBnD4NsdiIMaVsiAQK3AwloLKM3Xk", "elements": [], "paging": "urn:li:fs_volunteerExperienceView:ACoAAABZ9kgBnD4NsdiIMaVsiAQK3AwloLKM3Xk,paging", "$type": "com.linkedin.voyager.identity.profile.VolunteerExperienceView"}, {"firstName": "Josue", "lastName": "Hurtado", "$deletedFields": ["backgroundImage", "picture"], "occupation": "Librarian, Coordinator of Public Services & Outreach, Special Collections Research Center at Temple University Libraries", "objectUrn": "urn:li:member:5895752", "entityUrn": "urn:li:fs_miniProfile:ACoAAABZ9kgBnD4NsdiIMaVsiAQK3AwloLKM3Xk", "publicIdentifier": "josue-hurtado-a88b831", "trackingId": "fFYC3BaYRveIcmdu8LvDVw==", "$type": "com.linkedin.voyager.identity.shared.MiniProfile"}]}, "26": {"request": "/voyager/api/identity/profiles/josue-hurtado-a88b831/profileView", "status": 200, "body": "bpr-guid-316190"}, "27": {"data": {"shareVisibilityType": "PUBLIC", "$deletedFields": [], "sharePublicVisibilityTooltipMessage": "urn:li:fs_mySettings:476788719,sharePublicVisibilityTooltipMessage", "entityUrn": "urn:li:fs_mySettings:476788719", "dailyRundownPushNotificationAllowed": false, "videoAutoPlay": "ALWAYS", "flagshipCrossLinkToJobSearchApp": true, "discloseAsProfileViewer": "HIDE", "mobileCalendarsAutoSyncAllowed": true, "mobileContactsAutoSyncAllowed": true, "$type": "com.linkedin.voyager.common.MySettings"}, "included": [{"$deletedFields": [], "start": 72, "length": 10, "type": {"com.linkedin.pemberly.text.Hyperlink": "urn:li:fs_mySettings:476788719,sharePublicVisibilityTooltipMessage,attributes,2ac26525-80d8-4eab-8a74-e0752d590b7d-1,type,com.linkedin.pemberly.text.Hyperlink"}, "$type": "com.linkedin.pemberly.text.Attribute", "$id": "urn:li:fs_mySettings:476788719,sharePublicVisibilityTooltipMessage,attributes,2ac26525-80d8-4eab-8a74-e0752d590b7d-1"}, {"$deletedFields": [], "start": 21, "length": 6, "type": {"com.linkedin.pemberly.text.Bold": "urn:li:fs_mySettings:476788719,sharePublicVisibilityTooltipMessage,attributes,2ac26525-80d8-4eab-8a74-e0752d590b7d-0,type,com.linkedin.pemberly.text.Bold"}, "$type": "com.linkedin.pemberly.text.Attribute", "$id": "urn:li:fs_mySettings:476788719,sharePublicVisibilityTooltipMessage,attributes,2ac26525-80d8-4eab-8a74-e0752d590b7d-0"}, {"$deletedFields": [], "attributes": ["urn:li:fs_mySettings:476788719,sharePublicVisibilityTooltipMessage,attributes,2ac26525-80d8-4eab-8a74-e0752d590b7d-0", "urn:li:fs_mySettings:476788719,sharePublicVisibilityTooltipMessage,attributes,2ac26525-80d8-4eab-8a74-e0752d590b7d-1"], "text": "Now when you post to Public, it's visible to anyone on or off LinkedIn. Learn more.", "$type": "com.linkedin.pemberly.text.AttributedText", "$id": "urn:li:fs_mySettings:476788719,sharePublicVisibilityTooltipMessage"}, {"$deletedFields": [], "$type": "com.linkedin.pemberly.text.Bold", "$id": "urn:li:fs_mySettings:476788719,sharePublicVisibilityTooltipMessage,attributes,2ac26525-80d8-4eab-8a74-e0752d590b7d-0,type,com.linkedin.pemberly.text.Bold"}, {"$deletedFields": [], "url": "https://www.linkedin.com/help/linkedin/answer/82288?lang=en", "$type": "com.linkedin.pemberly.text.Hyperlink", "$id": "urn:li:fs_mySettings:476788719,sharePublicVisibilityTooltipMessage,attributes,2ac26525-80d8-4eab-8a74-e0752d590b7d-1,type,com.linkedin.pemberly.text.Hyperlink"}]}, "28": {"request": "/voyager/api/me/settings", "status": 200, "body": "bpr-guid-316191"}, "29": {"statuses": {}, "results": {"publicProfile.removeModulesExperiments": {"treatment": "control", "testKey": "publicProfile.removeModulesExperiments"}}, "errors": {}}, "30": {"request": "/voyager/api/lixTreatments?ids=List(publicProfile.removeModulesExperiments)&target=urn%3Ali%3Aurl%3A0", "status": 200, "body": "bpr-guid-316193"}}